Workbook

Sheet README
A1: Deep Tax Burden Study v35 | Publication Ready
A2: Fully inclusive mature replacement-year model with all validated revenue methods active. The Land Value Tax remains unchanged.
A3: Purpose | B3: Average mature replacement-year funding model for General Government, Social Security, Healthcare, and dedicated public funds.
A4: Source of truth | B4: Policy Book v91 plus user-approved revisions through Tax Overhaul v28 / Study v35.
A5: Headline revenue | B5: Operating General Treasury Revenue: $5.711T. Year 10 Total Government Revenue: $9.103T.
A6: Headline balance | B6: General Government: +$318.956B. Social Security: $0. Healthcare: +$376.509B. Year 10 consolidated surplus: +$1.080T.
A7: National Continuity Contribution | B7: 0.73% on covered enterprise value above $1M. Central assessed base: $68T. Social Security first, NIRF residual.
A8: Resident Contributor Number | B8: Noncitizens use the RCN and contribute 7% employee / 7% employer until citizenship.
A9: Citizen Data Royalty | B9: 30% of a $246.532B covered data-market base, producing $73.960B for the Citizen Wealth Fund.
A10: Luxury Tax | B10: Flat 5% on a $241.275B active market base, producing $12.064B.
A11: Expanded liquid income | B11: Includes pensions, annuities, IRA distributions, royalties, settlements, foreign cash income, and data-licensing payments.
A12: Anti-deferral | B12: 10% on covered Form 4797 gains, deferred like-kind gains, REMIC residual income, and related entity-retention methods.
A13: Industrial and behavioral revenue | B13: Outsourcing Penalty, Fair Profit Tax, Loan Scumming taxes, Protectorate Fee, Carbon Tax, and spectrum stewardship are active.
A14: Public-enterprise revenue | B14: NLA, NHDC international licensing, federal data services, laboratory licensing, industrial campuses, pipeline corridors, and commercial space services are included.
... A19: Formula integrity restored | B19: This publication restores 80 cells across 13 sheets that had been stripped to a bare equals sign in prior versions (present already in v33 Corrected and v34), plus several genuinely blank subtotal or placeholder rows (Cost_Savings_Program row 20, SS_Year_0_4_10 row 25, and three merged rows in Deficit_Views). Every recovered figure was verified against this file own prior cached values before recalculation; all 1,858 comparable numeric cells match to the cent, and all 41 active QA_Checks read PASS after a live LibreOffice recalculation.

Sheet 2024_Basis_Control
A1: 2024 Basis Control - Single-Year Inputs
A3: Input | B3: Value ($B) | C3: Use | D3: Source | E3: URL
A4: Personal income | B4: 24905.9 | C4: Individual tax; citizen-side SS | D4: FRED/BEA | E4: https://fred.stlouisfed.org/series/A065RC1A027NBEA
A5: Gross national income | B5: 28993.443 | C5: Guaranteed 5% citizen-side HSA credit | D5: World Bank/FRED | E5: https://fred.stlouisfed.org/series/MKTGNIUSA646NWDB
A6: Wages and salaries | B6: 11708.891 | C6: Employer SS, HSA, catastrophic pool | D6: FRED/BEA | E6: https://fred.stlouisfed.org/series/BA06RC1A027NBEA
A7: Corporate profits before tax | B7: 4179.16 | C7: Corporate tax base | D7: FRED/BEA | E7: https://fred.stlouisfed.org/series/A053RC1A027NBEA
A8: Federal receipts | B8: 4919 | C8: Current federal revenue | D8: CBO | E8: https://www.cbo.gov/publication/60843/html
A9: Federal outlays | B9: 6752 | C9: Current federal outlays | D9: CBO | E9: https://www.cbo.gov/publication/60843/html
A10: OASDI income | B10: 1418 | C10: Current SS income benchmark | D10: SSA | E10: https://www.ssa.gov/oact/TR/2025/III_A_cyoper.html
A11: OASDI cost | B11: 1485 | C11: SS cost target | D11: SSA | E11: https://www.ssa.gov/oact/TR/2025/III_A_cyoper.html
A12: National health expenditure | B12: 5300 | C12: Healthcare baseline | D12: CMS | E12: https://www.cms.gov/data-research/statistics-trends-and-reports/national-health-expenditure-data/nhe-fact-sheet
A13: Federal health sponsor pool | B13: 1643 | C13: NHDC catastrophic/public care fund | D13: CMS/NHE allocation | E13: https://www.cms.gov/data-research/statistics-trends-and-reports/national-health-expenditure-data/nhe-fact-sheet
A14: Employer government social-insurance contributions | B14: 866.444 | C14: Current employer burden | D14: FRED/BEA | E14: https://fred.stlouisfed.org/series/B039RC1A027NBEA
A15: Private business health sponsor pool | B15: 954 | C15: Current employer health burden | D15: CMS NHE | E15: https://www.cms.gov/data-research/statistics-trends-and-reports/national-health-expenditure-data/nhe-fact-sheet
... A24: FY2024 individual income tax receipts | B24: 2426 | C24: Current-system Before benchmark | D24: CBO/Treasury | E24: https://www.cbo.gov/publication/60843/html
A25: The statutory tax base is liquid personal income, defined in Liquid_Income_Base: wages and salaries, proprietors' income, monetary interest, monetary rental income, dividends, and realized capital gains, excluding government transfers, supplements to wages, and imputed (noncash) income. Headline BEA personal income is retained as a scale reference only and is no longer a tax base.
A26: Current-system comparators: FY2024 receipts $4,919B, outlays $6,752B, unified deficit -$1,833B; OASDI income $1,418B vs cost $1,485B = -$67B annual balance; corporate receipts about $530B; state/local property taxes $797B.
A28: Debt held by the public (end FY2024) | B28: 28200 | C28: Debt flywheel base | D28: US Treasury via FRED | E28: https://fred.stlouisfed.org/series/FYGFDPUN
A29: Net interest outlays (FY2024) | B29: 882 | C29: Interest expense baseline | D29: CBO/Treasury | E29: https://www.cbo.gov/publication/60843/html
A30: Effective average interest rate | B30: =B29/B28 -> 0.031276596 | C30: Derived: net interest / debt held by public | D30: Derived
A32: Proprietors' income (2024) | B32: 1970 | C32: Liquid base component | D32: BEA NIPA Table 2.1 / FRED PROPINC | E32: https://fred.stlouisfed.org/series/PROPINC
A33: Personal dividend income (2024) | B33: 1940 | C33: Liquid base component | D33: BEA NIPA Table 2.1 / FRED PDI | E33: https://fred.stlouisfed.org/series/PDI
A34: Personal interest income, monetary portion (2024) | B34: 1300 | C34: Liquid base component; excludes imputed interest | D34: BEA Table 2.1 / FRED PII, imputed removed [M] | E34: https://fred.stlouisfed.org/series/PII
A35: Rental income of persons, monetary portion (2024) | B35: 300 | C35: Liquid base component; excludes imputed owner-occupied rent | D35: BEA Table 2.1 monetary split [M] | E35: https://apps.bea.gov/iTable/?1903=58&1921=survey&reqid=19&step=3&isuri=1
A36: Equity compensation base (US public companies, latest FY) | B36: 366.7 | C36: Employer SS capital-wage base; equity surtax base | D36: Carver Edison SEC EDGAR dataset; MS Counterpoint $270B (2022) corroboration | E36: https://carveredison.com/research/stock-based-comp-report-2026/
A37: Vice sales base: alcohol+tobacco+gambling+cannabis (2024) | B37: 530 | C37: 5% sin sales surtax base | D37: Cannabis $30.1B Whitney Economics; alcohol/tobacco/gambling components [M], pin to industry sources | E37: https://cannabis.lacity.gov/articles/2024-us-cannabis-sales
A38: State/local government healthcare sponsor funding (2024) | B38: 848 | C38: Retained state/local healthcare funding | D38: CMS NHE sponsor share ~16% of NHE [M] | E38: https://www.cms.gov/data-research/statistics-trends-and-reports/national-health-expenditure-data/nhe-fact-sheet
A39: State/local employer-channel healthcare portion (2024) | B39: 190 | C39: Removed from sponsor funding to prevent double count | D39: 5%+5% of ~$1.9T state/local wages [M]
A40: State and local government wages (2024) | B40: 1900 | C40: State/local employer SS subcomponent display | D40: BEA govt compensation [M]
A41: Expanded liquid personal income base | B41: =Liquid_Income_Base!B16 -> 20470.758 | C41: Individual flat tax; citizen SS; citizen HSA tiers | D41: Liquid_Income_Base active total
A42: Retained current-law federal receipts | B42: 253 | C42: General Treasury receipts not replaced or repealed | D42: CBO FY2024 other receipts | E42: https://www.cbo.gov/publication/60843/html
A43: Policy source of truth | C43: Rates, bases, routing, and active mature-replacement treatment | D43: PolicyBook v86.0 plus approved corrections | E43: PolicyBook_v86_0.html
A44: Taxable IRA distributions | B44: 437.77558 | C44: Expanded liquid base | D44: IRS Publication 4801, TY2023 | E44: https://www.irs.gov/statistics/soi-tax-stats-individual-income-tax-returns-publication-1304-complete-report
A45: Taxable pensions and annuities | B45: 858.03834 | C45: Expanded liquid base | D45: IRS Publication 4801, TY2023 | E45: https://www.irs.gov/statistics/soi-tax-stats-individual-income-tax-returns-publication-1304-complete-report
A46: Estate and trust distributions | B46: 50.110198 | C46: Separate 3% tax base | D46: IRS Schedule E statistics | E46: https://www.irs.gov/statistics/soi-tax-stats-individual-income-tax-returns-publication-1304-complete-report
A47: Data-licensing payments to individuals | B47: 275 | C47: Expanded liquid base and corporate expense deduction | D47: Inherited active model base; direct 30% data tax removed
A48: Foreign cash income add-back | B48: 29.744257 | C48: Expanded liquid base | D48: IRS foreign earned income exclusion proxy | E48: https://www.irs.gov/statistics/soi-tax-stats-individual-income-tax-returns-publication-1304-complete-report

Sheet Liquid_Income_Base
A1: Liquid Personal Income Base - Expanded Active Tax Base
A2: One cash-availability definition governs the 10% individual tax, 3% citizen Social Security contribution, and 5% citizen-side HSA funding. Social Security and government assistance remain excluded. Data-licensing payments are income to the citizen rather than a separate data tax.
A3: Included component | B3: Active base ($B) | C3: 10% income tax ($B) | D3: 3% citizen SS ($B) | E3: 5% citizen-side HSA ($B) | F3: Source / treatment
A4: Wages and salaries | B4: =2024_Basis_Control!B6 -> 11708.891 | C4: =B4*10% -> 1170.8891 | D4: =B4*3% -> 351.26673 | E4: =B4*5% -> 585.44455 | F4: BEA/FRED BA06RC1A027NBEA
A5: Proprietors' and covered pass-through income | B5: =2024_Basis_Control!B32 -> 1970 | C5: =B5*10% -> 197 | D5: =B5*3% -> 59.1 | E5: =B5*5% -> 98.5 | F5: BEA/FRED PROPINC; partnership overlap controlled
A6: Personal dividend income | B6: =2024_Basis_Control!B33 -> 1940 | C6: =B6*10% -> 194 | D6: =B6*3% -> 58.2 | E6: =B6*5% -> 97 | F6: BEA/FRED PDI
A7: Personal interest income, monetary only | B7: =2024_Basis_Control!B34 -> 1300 | C7: =B7*10% -> 130 | D7: =B7*3% -> 39 | E7: =B7*5% -> 65 | F7: BEA/FRED PII less imputed interest
A8: Rental income excluding separately displayed royalties | B8: =2024_Basis_Control!B35-B9 -> 265.51241 | C8: =B8*10% -> 26.551241 | D8: =B8*3% -> 7.9653725 | E8: =B8*5% -> 13.275621 | F8: Existing $300B monetary rent/royalty line less IRS net royalties
A9: Royalties | B9: 34.487585 | C9: =B9*10% -> 3.4487585 | D9: =B9*3% -> 1.0346275 | E9: =B9*5% -> 1.7243792 | F9: IRS Schedule E net royalty income; explicitly included
A10: Realized capital gains | B10: =2024_Basis_Control!B20 -> 1600 | C10: =B10*10% -> 160 | D10: =B10*3% -> 48 | E10: =B10*5% -> 80 | F10: CBO central 2024 estimate
A11: Taxable IRA distributions | B11: 437.77558 | C11: =B11*10% -> 43.777558 | D11: =B11*3% -> 13.133267 | E11: =B11*5% -> 21.888779 | F11: IRS Publication 4801, Tax Year 2023
A12: Taxable pensions and annuities | B12: 858.03834 | C12: =B12*10% -> 85.803834 | D12: =B12*3% -> 25.74115 | E12: =B12*5% -> 42.901917 | F12: IRS Publication 4801, Tax Year 2023
A13: Legal settlements and other 1099-MISC cash income | B13: 51.308665 | C13: =B13*10% -> 5.1308665 | D13: =B13*3% -> 1.5392599 | E13: =B13*5% -> 2.5654332 | F13: IRS Publication 5385, Form 1099-MISC Box 3 proxy
A14: Foreign cash income currently excluded under federal rules | B14: 29.744257 | C14: =B14*10% -> 2.9744257 | D14: =B14*3% -> 0.89232771 | E14: =B14*5% -> 1.4872128 | F14: IRS Publication 4801, foreign earned income exclusion add-back
A15: Data-licensing payments to individuals | B15: 275 | C15: =B15*10% -> 27.5 | D15: =B15*3% -> 8.25 | E15: =B15*5% -> 13.75 | F15: Active model base inherited from prior $82.5B / 30% data-tax line; now routed as personal income
A16: Total active liquid personal income | B16: =SUM(B4:B15) -> 20470.758 | C16: =SUM(C4:C15) -> 2047.0758 | D16: =SUM(D4:D15) -> 614.12274 | E16: =SUM(E4:E15) -> 1023.5379 | F16: Full cash/liquid base before age and student micro-adjustments
A18: Separate Source-Level Taxes Outside the 10% Individual Liquid-Income Base
A19: Tax | B19: Active base ($B) | C19: Rate | D19: Revenue ($B) | E19: Reason for separate treatment | F19: Source / link
A20: Estate and trust distributions | B20: 50.110198 | C20: 0.03 | D20: =B20*C20 -> 1.5033059 | E20: User-approved 3% distribution levy rather than the 10% individual rate | F20: IRS Schedule E line 35 positive income
A21: Entity/transaction anti-deferral tax | B21: =Anti_Deferral_Tax!B9 -> 282.70996 | C21: 0.1 | D21: =Anti_Deferral_Tax!D9 -> 28.270996 | E21: Form 4797, like-kind deferred gain, REMIC and trade-up structures when no individual has received/solely owns the income | F21: Anti_Deferral_Tax
A23: Excluded from the liquid-income base
A24: Social Security benefits | E24: Explicitly excluded by policy
A25: Government benefits and public assistance | E25: Transfers rather than taxable earned/liquid income
A26: Return of previously taxed principal or basis | E26: Only economic income or gain is taxed
A27: Imputed interest, imputed owner-occupied rent, and other noncash accounting income | E27: Not available for the person to spend
A29: The 0% full-time-student wage treatment and 5% low-net-worth youth/elderly rate remain statutory. This national active model applies the headline 10% rate until taxpayer-level microdata can allocate those reduced rates without inventing a population split.

Sheet Tax_Revenue_2024
A1: 2024 Proposed Revenue — Fully Inclusive Studied Mature Replacement Model
A2: Every Policy Book revenue method is now included or explicitly shown at zero when deterrence-only. LVT remains unchanged by instruction. Dedicated receipts and public-enterprise earnings remain segregated from operating Treasury.
A3: Revenue line | B3: Basis | C3: Rate | D3: Amount ($B) | E3: Type | F3: Notes
A4: Individual income tax | B4: Expanded liquid personal income | C4: 0.1 | D4: =Liquid_Income_Base!C16 -> 2047.0758 | E4: General Treasury | F4: 10% on active liquid base; Social Security and public assistance excluded
A5: Corporate income tax central effective case | B5: Adjusted corporate profit base | C5: 0.1 | D5: =Corporate_Tax_Clear!E11 -> 390.416 | E5: General Treasury | F5: 15% statutory; active 10% effective Treasury rate after credits/deployment
A6: Estate and trust distribution tax | B6: Positive estate/trust distributions | C6: 0.03 | D6: =Liquid_Income_Base!D20 -> 1.5033059 | E6: General Treasury | F6: Separate 3% levy
A7: Entity/transaction anti-deferral tax | B7: Form 4797 + deferred like-kind + positive REMIC base | C7: 0.1 | D7: =Anti_Deferral_Tax!D9 -> 28.270996 | E7: General Treasury | F7: Source-level anti-loophole tax with individual-distribution credit
A8: Employer equity compensation surtax | B8: Equity compensation base, 9% aggregate | C8: 0.09 | D8: =Equity_Compensation!D19 -> 33.003 | E8: General Treasury | F8: Approved marginal schedule through $1M; upper tranche set at adoption
A9: Outsourcing Penalty | B9: Related-party manufacturing-import proxy | C9: 0.1 | D9: =Outsourcing_Penalty!D9 -> 142.92019 | E9: General Treasury | F9: Active proxy for companies outsourcing >50% of manufacturing
A10: Fair Profit Tax | B10: Original 2024 market screening study | D10: =Fair_Profit_Study!I16 -> 3.3070532 | E10: General Treasury | F10: PolicyBook calculator applied to qualifying mass-produced physical goods
A11: Loan Scumming taxes and fees | B11: Large-debt payoff plus 10-year audit recharacterization | D11: =Loan_Scumming!D14 -> 7.95 | E11: General Treasury | F11: 5% payoff tax plus retroactive 10% income tax
A12: Protectorate Fee | B12: 77-country legacy expenditure base | C12: 0.01 | D12: =Protectorate_Fee!F82 -> 151.4038 | E12: General Treasury | F12: 1% of covered government expenditure
A13: Flat Luxury Tax | B13: Qualified luxury-goods and luxury-asset sales | C13: 0.05 | D13: =Luxury_Tax!F10 -> 12.06373 | E13: General Treasury | F13: Flat 5% on the active Luxury_Tax market base
A14: Citizen Data Royalty | B14: Commercial monetization of U.S. citizen data | C14: 0.3 | D14: =Citizen_Data_Royalty!J13 -> 73.959598 | E14: Dedicated collection: Citizen Wealth Fund | F14: Collected by General Government; transferred in full to the CWF
A15: Sin sales surtax | B15: Alcohol, tobacco, gambling, marijuana sales | C15: 0.05 | D15: =2024_Basis_Control!B37*C15 -> 26.5 | E15: Earmarked: NHDC catastrophic | F15: Excluded from Treasury subtotal
A16: Federalized LVT | B16: Full federal land-rent capture target | D16: =2024_Basis_Control!B16 -> 2232.929 | E16: General Treasury | F16: Full $2.233T active scenario; primary residence exempt
A17: 1% national resource royalty | B17: Mining/extraction plus forestry | C17: 0.01 | D17: =Resource_Royalty!D6 -> 7.53102 | E17: General Treasury | F17: See Resource_Royalty
A18: Energy export excise | B18: Covered energy export sales | C18: 0.05 | D18: =Energy_Export_Excise!D12 -> 16.84285 | E18: General Treasury | F18: Active 5% deficit-year rate; returns to 4% after the prior-year consolidated budget is balanced
A19: Retained current-law federal receipts | B19: Receipt classes not replaced or repealed | D19: 253 | E19: General Treasury | F19: Customs, current excises, estate/gift receipts, fees, remittances, miscellaneous
A20: Idle Wealth Levy | B20: Certified concentrated nonproductive financial-reserve base | C20: 0.01 | D20: =Idle_Wealth_Levy!F13 -> 47.714505 | E20: General Treasury | F20: 1% excise; managers withhold for clients on covered managed assets; no cross-tier credit
A21: Offshore Capital Export Duty | B21: Covered passive outbound capital after U.S.-company expansion carveout | C21: 0.1 | D21: =Offshore_Capital_Duty!F12 -> 19.2 | E21: General Treasury | F21: 10% duty; central behavioral budget score
A22: High-Wealth Withholding and Compliance Recovery | B22: Existing unpaid liability collected at controlled intermediaries | D22: =High_Wealth_Compliance!F9 -> 38 | E22: General Treasury | F22: Collection mechanism; no new statutory tax rate
A23: Cross-policy overlap adjustment | B23: Overlap between offshore-duty and compliance-recovery channels | D23: -4 | E23: General Treasury | F23: Prevents double counting the same enforcement recovery
A24: Carbon Tax | B24: 2024 energy-related CO2 emissions × studied $25/t × 90% mature base | C24: 25 | D24: 107.4 | E24: General Treasury | F24: Studied rate and response; Policy Book rate was previously unspecified
A25: Spectrum stewardship: General Treasury share | B25: Auction, transfer, annual rent and vacancy fees | D25: 5 | E25: General Treasury | F25: Gross $12B; $6B to NIRF and $1B administration
A26: National laboratory patent marketplace | B26: Unified licensing and commercialization marketplace | D26: 0.4 | E26: General Treasury | F26: Net of $0.1B administration
A27: Federal Enterprise Data Services | B27: Enterprise subscriptions, processing and redistribution licenses | D27: 2 | E27: General Treasury | F27: Net of $1B operating cost
A28: Industrial campus leases and services | B28: Ground leases, utility contracts, testing, security and royalties | D28: 10 | E28: General Treasury | F28: Net of $5B campus operations
A29: Pipeline corridor capacity auctions | B29: National corridor capacity, ROW rents and auction fees | D29: 3.5 | E29: General Treasury | F29: Net of $0.5B administration
A30: Commercial space infrastructure | B30: Orbital, tracking, navigation and launch infrastructure services | D30: 3 | E30: General Treasury | F30: Net of $2B operations
A31: Patent troll penalties | B31: Covered abusive assertion penalties | D31: 0.5 | E31: General Treasury | F31: Small deterrence-based central estimate
A32: NIRF distributable investment return | B32: Mature protected corpus return under statutory transfer ceiling | D32: 150 | E32: General Treasury | F32: Studied $7.5T corpus, 4% real return, 50% transfer ceiling
A33: Unrestricted General Treasury subtotal | B33: All unrestricted external General revenue | D33: =SUM(D4:D13)+SUM(D16:D23)+SUM(D24:D32) -> 5710.9312 | E33: General Treasury | F33: Includes newly studied methods; excludes dedicated receipts
A34: Gross General-administered collections | B34: Treasury subtotal plus Citizen Data Royalty | D34: =D33+D14 -> 5784.8908 | E34: General administration | F34: Shows universal federal collection channel
A35: Citizen Wealth Fund transfer | B35: Equal to Citizen Data Royalty | D35: 73.959598 | E35: Dedicated outlay | F35: Full transfer; no ordinary Treasury availability
A36: NIRF capital receipt: spectrum share | B36: Spectrum auctions and rent allocation | D36: 6 | E36: Dedicated NIRF principal | F36: External receipt and protected asset purchase
A37: NHDC international license earnings | B37: International product and manufacturing licenses | D37: 12 | E37: Dedicated healthcare | F37: Separate from export margin
A38: NLA institutional/international earnings | B38: Institutional servicing and international lending | D38: 12 | E38: Dedicated Social Security | F38: Separate from domestic NLA distributable profit

Sheet Equity_Compensation
A1: Capital Wages - Employer Social Security Base Expansion and Employer Equity Compensation Surtax
A3: Line | B3: Basis | C3: Rate | D3: Amount ($B) | E3: Notes
A4: Equity compensation base | B4: US public companies, latest FY, SEC EDGAR aggregate | D4: =2024_Basis_Control!B36 -> 366.7 | E4: Carver Edison $366.7B across 1,680 issuers; Morgan Stanley Counterpoint ~$270B (2022) corroborates scale; private-company grants are upside
A5: Employer SS on cash wages | B5: Wages and salaries | C5: 0.03 | D5: =2024_Basis_Control!B6*C5 -> 351.26673 | E5: Unchanged 3% employer rate
A6: Employer SS on capital wages | B6: Equity compensation at fair value on transfer/vesting/settlement | C6: 0.03 | D6: =2024_Basis_Control!B36*C6 -> 11.001 | E6: Equity counted the same as cash; $5M grant owes $150K
A7: Total employer SS contribution | B7: Cash + capital wages | D7: =D5+D6 -> 362.26773 | E7: Carried into SS_Hybrid_2024
A8: State/local employer subcomponent (display) | B8: State/local government wages | C8: 0.03 | D8: =2024_Basis_Control!B40*C8 -> 57 | E8: Shown as a distinct line inside the national employer base; never additive
A10: Employer Equity Compensation Surtax - progressive, employer-paid, per employee per year
A11: Annual equity compensation per employee | B11: Marginal rate
A12: $1,000 or less | B12: 0
A13: Above $1,000 to $10,000 | B13: 0.05
A14: $10,000 to $100,000 | B14: 0.075
A15: $100,000 to $1,000,000 | B15: 0.1
A16: Above $1,000,000 | B16: Set at adoption
A18: Effective aggregate rate [M] | B18: 0.09 | E18: Active aggregate implementation rate across the documented equity-compensation base; upper statutory tranche remains set at adoption
A19: Surtax revenue | D19: =2024_Basis_Control!B36*B18 -> 33.003 | E19: Active General Treasury revenue line in Tax_Revenue_2024
A20: Three separated tax events remain active: employer Social Security on compensation value; employer equity surtax on the same value; and employee tax on later realized appreciation. Grants aggregate per employee per employer per tax period and apply marginally.

Sheet Corporate_Tax_Clear
A1: Corporate Tax - Gross Profit, Data-Licensing Deduction, and PolicyBook Rates
A3: Line | B3: Meaning | C3: Base ($B) | D3: Rate | E3: Treasury Revenue ($B) | F3: Non-Treasury Deployment ($B) | G3: Notes
A4: Gross corporate profit base | B4: 2024 profits before tax | C4: 4179.16 | G4: BEA corporate profits before tax
A5: Less: data-licensing payments to individuals | B5: Corporate expense transferred into personal liquid income | C5: 275 | G5: Avoids counting the same payment as corporate profit and personal income
A6: Adjusted corporate tax base | B6: Gross profit less modeled data-license payments | C6: =C4-C5 -> 3904.16 | G6: Active central base
A7: Current statutory CIT rate | B7: Legal rate, not collection | C7: =C4 -> 4179.16 | D7: 0.21 | G7: Current-law benchmark
A8: Current actual CIT receipts | B8: FY2024 actual federal receipts | E8: 530 | G8: Benchmark
A9: Current effective receipts rate | B9: Receipts / gross base | C9: =C4 -> 4179.16 | D9: =E8/C9 -> 0.12681974 | G9: Formula
A10: Proposed minimum direct tax | B10: 5% minimum paid after ordinary active reductions | C10: =C6 -> 3904.16 | D10: 0.05 | E10: =C10*D10 -> 195.208 | G10: PolicyBook minimum except qualifying real-investment exemption
A11: Proposed central effective Treasury tax | B11: 15% statutory rate after central active credits/deployment provisions | C11: =C6 -> 3904.16 | D11: 0.1 | E11: =C11*D11 -> 390.416 | G11: Active revenue bridge
A12: Proposed statutory rate before reductions | B12: PolicyBook v86 corporate rate | C12: =C6 -> 3904.16 | D12: 0.15 | E12: =C12*D12 -> 585.624 | G12: Ceiling before active credits
A13: Productive deployment channel | B13: Up to 5% reinvestment, bonuses, and covered support | C13: =C6 -> 3904.16 | D13: 0.05 | E13: 0 | F13: =C13*D13 -> 195.208 | G13: Not Treasury revenue

Sheet SS_Hybrid_2024
A1: Social Security - Expanded Liquid-Income Active Mature Replacement Year
A3: Line | B3: Basis | C3: Rate | D3: Amount ($B) | E3: Notes
A4: Current OASDI income | B4: SSA 2024 | D4: 1418 | E4: Benchmark
A5: Gross OASDI cost before payment-accuracy saving | B5: SSA 2024 gross cost | D5: 1485 | E5: Published gross benchmark; the dynamic path deducts the separately booked $6B payment-accuracy saving
A6: Citizen contribution | B6: 3% of expanded liquid personal income | C6: 0.03 | D6: =2024_Basis_Control!B41*C6 -> 614.12274 | E6: Uncapped; includes pensions, annuities, legal/misc cash, foreign cash, royalties, and data-licensing income
A7: Employer contribution | B7: 3% of all compensation: wages plus equity at fair value | C7: 0.03 | D7: =Equity_Compensation!D7 -> 362.26773 | E7: Capital wages covered; see Equity_Compensation
A8: of which: state/local government employers (display) | B8: 3% of state/local wages | C8: 0.03 | D8: =Equity_Compensation!D8 -> 57 | E8: Distinct subcomponent; already inside the wage base; never counted twice
A9: Hybrid SS subtotal | B9: Citizen + employer | D9: =D6+D7 -> 976.39047 | E9: Before NLA transfer
A10: Mature NLA profit transfer (baseline) | B10: Audited distributable NLA profit at mature scale | D10: =NLA_Model!E23 -> 154.13732 | E10: Mature replacement system is the headline baseline; initial/central are transition sensitivities
A11: Trust investment income (central) | B11: 50% CWF index / 50% diversified on reserves | D11: =SS_Trust_Investment!C12 -> 193.05 | E11: Income generated from protected $2.7T trust floor
A12: SS funding at mature baseline | B12: Hybrid + mature NLA + trust income | D12: =SUM(D9:D11) -> 1323.5778 | E12: Dedicated funding
A13: SS surplus/gap at mature baseline before RCN and payment accuracy | B13: Funding minus $1.485T gross cost | D13: =D12-D5 -> -161.42221 | E13: Gross-cost view; later tables show the $1.479T net obligation after the $6B dedicated payment-accuracy saving
A14: Noncitizen 7%/7% incremental contribution | B14: Noncitizen liquid income + employer compensation above baseline 3%/3% | D14: =Noncitizen_SS_Model!B17 -> 52.407964 | E14: See Noncitizen_SS_Model
A15: Noncitizen OASDI benefit exclusion saving | B15: Central modeled mature-year amount | D15: =Noncitizen_SS_Model!B21 -> 18 | E15: No benefits accrue while noncitizen
A16: Revised SS surplus/gap after citizen-only policy | B16: Funding plus savings less OASDI cost | D16: =D13+D14+D15 -> -91.014251 | E16: Before healthcare waterfall
A17: Central NLA year | B17: =NLA_Model!E22 -> 67.71298 | D17: =D9+B17+SS_Trust_Investment!C12-D5 -> -247.84655 | E17: Intermediate gap
A19: Gap-closure levers sit in Gap_Closure. Expanded income materially narrows the SS gap while preserving the adopted 3% citizen and 3% employer rates.

Sheet Gap_Closure
A1: Residual Funding Gaps - Offshore Duty and High-Wealth Recovery Added
A2: U.S.-company foreign operating expansion is carved out of the Offshore Capital Export Duty. Passive wealth export remains covered.
A3: Measure / lever | B3: Amount ($B) or rate | C3: Notes
A4: Pre-change consolidated replacement gap | B4: -28.759626 | C4: v23 baseline
A5: Energy Export Excise increase, 4% to 5% | B5: 3.36857 | C5: Automatic deficit-year setting
A6: Idle Wealth Levy, central case | B6: =Idle_Wealth_Levy!F13 -> 47.714505 | C6: 1% of direct and managed nonproductive financial-reserve bases
A7: Offshore Capital Export Duty | B7: =Offshore_Capital_Duty!F12 -> 19.2 | C7: Central score after full direct-investment expansion carveout
A8: High-Wealth withholding and compliance recovery | B8: =High_Wealth_Compliance!F9 -> 38 | C8: Existing liabilities collected earlier and more completely
A9: Cross-policy overlap adjustment | B9: -4 | C9: Prevents double counting
A10: Revised consolidated replacement balance | B10: =B4+B5+B6+B7+B8+B9 -> 75.523448 | C10: Positive = recurring surplus
A11: Revised General Government balance before SS support | B11: =Deficit_Views!B43 -> 318.95606 | C11: Healthcare and SS ledgers unchanged
A12: Social Security dedicated gap | B12: =Deficit_Views!B45 -> 0 | C12: Still visible as a dedicated-ledger gap
A13: Healthcare dedicated reserve | B13: =Deficit_Views!B44 -> 376.50949 | C13: Still retained in Healthcare
A14: Previous v25 consolidated balance
A15: Current-system unified federal balance | B15: -1833 | C15: FY2024 benchmark
A16: Further reserve mechanisms | B16: 0 | C16: NIRF and spectrum revenue remain unbooked until fiscal valuation is completed

Sheet SS_Trust_Investment
A1: Social Security Trust Investment - Protected $2.7T Floor | 50% Citizen Wealth Fund Index / 50% Diversified
A3: Line | B3: Basis | C3: Rate/Share | D3: Amount ($B) | E3: Notes
A4: OASDI asset reserves (end 2024) | B4: SSA 2025 Trustees Report | D4: 2700 | E4: Statutory minimum corpus protected by Treasury backstop
A5: CWF index sleeve share | B5: Statutory allocation | C5: 0.5 | D5: =D4*C5 -> 1350 | E5: 50% in Citizen Wealth Fund index
A6: Diversified sleeve share | B6: Bonds/hard reserves/stable holdings | C6: 0.5 | D6: =D4*C6 -> 1350 | E6: Remaining 50%
A7: CWF index long-run nominal return (central) | B7: US equity total return 1928-2024 | C7: 0.099 | E7: Damodaran/NYU historical returns
A8: Diversified sleeve yield (central) | B8: 10-year Treasury, 2024 average | C8: 0.044 | E8: FRED DGS10
A10: Scenario | B10: Blended yield | C10: Trust investment income ($B) | D10: Assumption
A11: Conservative | B11: =(0.08+0.044)/2 -> 0.062 | C11: =D4*B11 -> 167.4 | D11: Equity sleeve at 8.0%
A12: Central | B12: =(C7+C8)/2 -> 0.0715 | C12: =D4*B12 -> 193.05 | D12: Equity at 9.9%, bonds at 4.4%
A13: Optimistic | B13: =(0.11+0.044)/2 -> 0.077 | C13: =D4*B13 -> 207.9 | D13: Equity sleeve at 11.0%
A15: Current-law comparison
A16: Special-issue effective rate (approx.) | B16: 0.025 | C16: =D4*B16 -> 67.5 | D16: SSA trust fund interest rates
A17: Incremental income, central vs current | C17: =C12-C16 -> 125.55 | D17: Yield gained by investing the trust
A19: The allocation is fixed in statute at 50% Citizen Wealth Fund index and 50% diversified holdings, rebalanced on schedule and published in full at every audit. Returns are long-run nominal averages; single-year sequence-of-returns risk requires the diversified sleeve and reserve discipline during the transition. Central income is carried into the Social Security funding bridge.

Sheet Healthcare_3_5_5
A1: Healthcare - Expanded Liquid-Income Active Mature Replacement Year
A3: Line | B3: Basis | C3: Rate | D3: Amount ($B) | E3: Layer | F3: Notes
A4: Current healthcare baseline | B4: CMS 2024 NHE | D4: 5300 | E4: Current cost | F4: Gross-price current system
A5: Conservative structural savings | B5: 20% cost reduction | C5: -0.2 | D5: =D4*C5 -> -1060 | E5: Cost reduction | F5: Conservative floor
A6: Proposed cost target at 20% savings | B6: NHE less savings | D6: =D4+D5 -> 4240 | E6: Cost target | F6: Funding target
A7: Citizen-paid HSA | B7: Tiered 2/3/5% on liquid personal income | D7: =2024_Basis_Control!B41*0.05*0.72527 -> 742.34133 | E7: HSA basic care | F7: Tier mix share 72.527% retained from v18 [M]; expanded liquid-income base applies
A8: Federal HSA supplement | B8: Top-up to the 5% citizen-side credit on liquid income | D8: =2024_Basis_Control!B41*0.05-D7 -> 281.19657 | E8: HSA basic care | F8: Federal top-up to maintain the full 5% citizen-side HSA funding floor
A9: Employer HSA match | B9: 5% of wages | C9: 0.05 | D9: =2024_Basis_Control!B6*C9 -> 585.44455 | E9: HSA basic care | F9: Portable worker-owned HSA
A10: Total HSA basic/direct care pool | B10: Citizen + federal + employer | D10: =SUM(D7:D9) -> 1608.9824 | E10: HSA basic care | F10: Routine/direct care
A11: Federal health sponsor pool | B11: Redirected current federal health pool | D11: =2024_Basis_Control!B13 -> 1643 | E11: NHDC catastrophic/public | F11: Transfer from the General Government silo
A12: State/local governmental healthcare funding | B12: Retained sponsor funding net of employer channels | D12: =2024_Basis_Control!B38-2024_Basis_Control!B39 -> 658 | E12: NHDC catastrophic/public | F12: Shift: state/local funding is retained in the national floor; employer-channel dollars removed to prevent double count
A13: NHDC domestic operating margin | B13: Domestic manufacturing under the three-times-cost ceiling | D13: 100 | E13: Internal operating result | F13: Retained inside the healthcare system but excluded from external funding to avoid double counting patient payments
A14: NHDC International Exports margin | B14: Mature export scenario (baseline) | D14: =NHDC_Exports!D10 -> 82.5825 | E14: External healthcare funding | F14: Foreign customer funds the domestic mission; see NHDC_Exports
A15: Public hospital operating surplus | B15: Public hospital operating result | D15: 13 | E15: Internal operating result | F15: Retained for operations and improvements but excluded from external funding
A16: Sin sales surtax earmark | B16: 5% of vice sales (§2) | C16: 0.05 | D16: =2024_Basis_Control!B37*C16 -> 26.5 | E16: NHDC catastrophic/public | F16: Statutory routing; excluded from Treasury
A17: External catastrophic/public-care funding | B17: Federal sponsor + state/local + exports + sin surtax | D17: =SUM(D11:D12)+D14+D16 -> 2410.0825 | E17: NHDC catastrophic/public | F17: Excludes domestic NHDC margin and public-hospital surplus
A18: Employer Catastrophic Care-Pool contribution | B18: 5% of wages | C18: 0.05 | D18: =2024_Basis_Control!B6*C18 -> 585.44455 | E18: Catastrophic pool | F18: Restricted national care pool
A19: Total external healthcare funding | B19: HSA + external catastrophic/public + employer pool | D19: =D10+D17+D18 -> 4604.5095 | E19: All layers | F19: No internal provider margin counted as new funding
A20: Healthcare reserve/gap at 20% savings | B20: Funding - cost target | D20: =D19-D6 -> 364.50949 | E20: Result | F20: Positive = reserve
A21: Central 22% savings target | B21: NHE less 22% | C21: -0.22 | D21: =D4*(1+C21) -> 4134 | E21: Sensitivity | F21: Reference central estimate
A22: Reserve/gap at 22% | B22: Funding - 22% target | D22: =D19-D21 -> 470.50949 | E22: Sensitivity | F22: Positive = reserve
A23: Internal retained operating margins | B23: NHDC domestic margin + public-hospital surplus | D23: =D13+D15 -> 113 | E23: Memo only | F23: Shown for transparency; excluded from funding and consolidated revenue
A24: State supplements above the national floor are state-funded and remain outside this national average-year breakeven. Transition costs, capital build-out, and unrelated general policies are not included in this replacement baseline.

Sheet NHDC_Exports
A1: NHDC International Exports - Three-Times-Cost Ceiling for the Citizen, At Market for the World
A3: Line | B3: Basis | C3: Share/Margin | D3: Amount ($B) | E3: Notes
A4: Global generic pharmaceuticals market (2024) | B4: Statista / Grand View | D4: =2024_Basis_Control!B22 -> 455 | E4: Addressable export market
A5: Net export margin assumption | B5: Public producer under a domestic three-times-cost ceiling selling abroad at market prices; no marketing or shareholder cost | C5: 0.55 | E5: Scenario assumption; documented, not sourced
A7: Scenario | B7: Global share | C7: Export revenue ($B) | D7: Net margin to catastrophic fund ($B)
A8: Initial | B8: 0.05 | C8: =D4*B8 -> 22.75 | D8: =C8*$C$5 -> 12.5125
A9: Central | B9: 0.2 | C9: =D4*B9 -> 91 | D9: =C9*$C$5 -> 50.05
A10: Mature | B10: 0.33 | C10: =D4*B10 -> 150.15 | D10: =C10*$C$5 -> 82.5825
A12: Every dollar of export margin routes to the domestic mission: the catastrophic care fund, safety-net hospitals, and expanded manufacturing capacity. The central scenario (20% global share) reflects a state manufacturer with US regulatory standing undercutting global generic cartels; India today supplies roughly 40% of US generic volume, so large single-nation shares are precedented. Domestic essential generics sell under a statutory price ceiling of three times cost (maximum 200% margin), with the headroom retiring research and development cost; domestic profit remains inside the Healthcare silo and is never Treasury revenue. The mature scenario is the replacement-budget baseline.

Sheet Employer_Burden
A1: Employer Burden - Current Benchmark vs Proposed 3+5+5
A3: Line | B3: Current ($B) | C3: Proposed ($B) | D3: Formula/Basis | E3: % Payroll | F3: Notes
A4: Employer gov social-insurance contributions | B4: 866.444 | D4: Current FRED benchmark | E4: =B4/2024_Basis_Control!B6 -> 0.07399881 | F4: Current
A5: Private business health sponsor pool | B5: 954 | D5: CMS private business health sponsor pool | E5: =B5/2024_Basis_Control!B6 -> 0.081476546 | F5: Current
A6: Current employer burden benchmark | B6: =SUM(B4:B5) -> 1820.444 | D6: Current social + health | E6: =B6/2024_Basis_Control!B6 -> 0.15547536 | F6: Broad benchmark
A7: Social Security employer match | C7: =2024_Basis_Control!B6*3% -> 351.26673 | D7: 3% wages | E7: =C7/2024_Basis_Control!B6 -> 0.03 | F7: Payroll-based
A8: Portable HSA match | C8: =2024_Basis_Control!B6*5% -> 585.44455 | D8: 5% wages | E8: =C8/2024_Basis_Control!B6 -> 0.05 | F8: Minimum; employers can offer more
A9: Catastrophic Care-Pool contribution | C9: =2024_Basis_Control!B6*5% -> 585.44455 | D9: 5% wages | E9: =C9/2024_Basis_Control!B6 -> 0.05 | F9: National pool
A10: Proposed employer burden | C10: =SUM(C7:C9) -> 1522.1558 | D10: 13% payroll | E10: =C10/2024_Basis_Control!B6 -> 0.13 | F10: Stable payroll-based
A11: Employer burden reduction / increase | C11: =B6-C10 -> 298.28817 | D11: Current - proposed | E11: =C11/2024_Basis_Control!B6 -> 0.025475356 | F11: Positive = savings
A12: Small-business relief/credit pool | C12: 10 | D12: General-budget surge reserve | F12: Transition relief plus national-lockdown/disaster surge fund; the reserve also serves as the administrative chassis for emergency appropriations, so $10B is standing capacity and the pipe, not the ceiling.

Sheet LVT_External_Validation
A1: External LVT Validation - Federalized Land-Rent Capture by Land Type
A3: Land / benchmark type | B3: External value | C3: Units | D3: Illustrative treatment | E3: Illustrative rate | F3: Potential revenue ($B) | G3: Source | H3: Validation limitation
A4: Current state/local property-tax collections | B4: 797 | C4: $B | D4: Replacement benchmark | G4: https://eyeonhousing.org/tag/state-and-local-tax-revenue/ | H4: Includes improvements as well as land; benchmark only.
A5: U.S. farm real estate | B5: 4170 | C5: $/acre | D5: Agricultural reference | E5: 0.01 | G5: https://www.nass.usda.gov/Publications/Todays_Reports/reports/land0824.pdf | H5: Farm real estate includes land and buildings.
A6: U.S. cropland | B6: 5570 | C6: $/acre | D6: Lower-rate productive land | E6: 0.01 | G6: https://www.nass.usda.gov/Publications/Todays_Reports/reports/land0824.pdf | H6: Per-acre national average; acreage/appraisal needed.
A7: U.S. pasture | B7: 1830 | C7: $/acre | D7: Lower-rate grazing land | E7: 0.005 | G7: https://www.nass.usda.gov/Publications/Todays_Reports/reports/land0824.pdf | H7: Per-acre national average; acreage/appraisal needed.
A8: Household/nonprofit real estate | B8: 52987.317 | C8: $B | D8: Residential scale anchor; primary homes exempt operationally | G8: https://fred.stlouisfed.org/series/HNOREMV | H8: Land and structures combined; Q1 2026 scale anchor, not taxable base.
A9: Nonfinancial corporate real estate | B9: 15694.221 | C9: $B | D9: Commercial/industrial scale anchor | G9: https://fred.stlouisfed.org/series/BOGZ1LM105035005A | H9: Land and structures combined.
A10: Noncorporate business real estate | B10: 17463.06 | C10: $B | D10: Rental/commercial scale anchor | G10: https://fred.stlouisfed.org/series/NNCBIRER | H10: Land and structures combined; Q1 2026 scale anchor.
A11: Vacant/speculative urban land | B11: Parcel appraisal required | C11: - | D11: Higher capture rate | G11: Local assessment rolls / federal parcel model | H11: No national land-only total presently used.
A12: Second homes / non-primary residential land | B12: Parcel appraisal required | C12: - | D12: Residential LVT applies | G12: County assessment records / federal parcel model | H12: Primary residence exemption must be separated parcel by parcel.
A13: Mineral rights / extraction lease value | B13: Royalty model separate | C13: - | D13: Avoid double counting with resource royalty | G13: Federal/state lease records | H13: LVT applies to location rent; extraction royalty applies to removed resource.
A15: Model target reconciliation | B15: Amount ($B) | C15: Formula / status
A16: Current property-tax replacement benchmark | B16: 797 | C16: Externally benchmarked
A17: Federalized LVT target | B17: 2232.929 | C17: Policy target pending parcel-level validation
A18: Additional federal land-rent capture | B18: =B17-B16 -> 1435.929 | C18: Target less current benchmark
A19: LVT scale ratio | B19: =B17/B16 -> 2.8016675 | C19: Target / property-tax benchmark
A21: The LVT target is retained as a policy scenario, not represented as fully proven. A national parcel-level model must separate land from improvements, primary residences from taxable residential land, and productive agricultural land from speculative or high-rent urban land.
A22: IMPLIED CAPTURE RATE AGAINST THE FEDERAL RESERVE REAL-ESTATE ENVELOPE
A23: Measure | B23: Value | C23: Unit | D23: Formula | E23: Interpretation | F23: Source | G23: Status | H23: Limitation
A24: Combined Fed real-estate envelope | B24: =SUM(B8:B10) -> 86144.598 | C24: $B | D24: Household/nonprofit + corporate + noncorporate real estate | E24: Broad upper envelope that includes structures | F24: Federal Reserve/FRED series listed above | G24: External | H24: Not land-only
A25: Federalized LVT target | B25: =B17 -> 2232.929 | C25: $B | D25: Active policy target | E25: Booked revenue | F25: Policy model | G25: Adopted | H25: Pending parcel validation
A26: Target / full real-estate envelope | B26: =B25/B24 -> 0.025920708 | C26: Annual share | D26: LVT target divided by land-and-structures envelope | E26: Lower-bound implied capture rate because structures and exempt primary homes remain in the denominator | F26: Calculated | G26: Calculated | H26: True taxable-land rate will be higher
A27: Illustrative taxable land-only base | B27: =B24*40%*50% -> 17228.92 | C27: $B | D27: 40% land share × 50% taxable share after exemptions | E27: Central disclosure scenario, not a parcel estimate | F27: Model disclosure assumption | G27: Illustrative | H27: Actual land and exemption shares require parcel data
A28: Implied rate on illustrative taxable land-only base | B28: =B25/B27 -> 0.12960354 | C28: Annual share | D28: LVT target divided by illustrative taxable land-only base | E28: Shows the parcel study must validate a materially higher land-only rate | F28: Calculated | G28: Calculated | H28: Sensitivity, not legal validation
A30: Land share | B30: Taxable share after exemptions | C30: Taxable land base ($B) | D30: Implied annual LVT rate | E30: Interpretation
A31: 0.3 | B31: 0.35 | C31: =$B$24*A31*B31 -> 9045.1828 | D31: =$B$25/C31 -> 0.24686389 | E31: Illustrative sensitivity; parcel model required
A32: 0.3 | B32: 0.5 | C32: =$B$24*A32*B32 -> 12921.69 | D32: =$B$25/C32 -> 0.17280472 | E32: Illustrative sensitivity; parcel model required
A33: 0.3 | B33: 0.65 | C33: =$B$24*A33*B33 -> 16798.197 | D33: =$B$25/C33 -> 0.13292671 | E33: Illustrative sensitivity; parcel model required
A34: 0.4 | B34: 0.35 | C34: =$B$24*A34*B34 -> 12060.244 | D34: =$B$25/C34 -> 0.18514792 | E34: Illustrative sensitivity; parcel model required
A35: 0.4 | B35: 0.5 | C35: =$B$24*A35*B35 -> 17228.92 | D35: =$B$25/C35 -> 0.12960354 | E35: Illustrative sensitivity; parcel model required
A36: 0.4 | B36: 0.65 | C36: =$B$24*A36*B36 -> 22397.595 | D36: =$B$25/C36 -> 0.099695032 | E36: Illustrative sensitivity; parcel model required
A37: 0.5 | B37: 0.35 | C37: =$B$24*A37*B37 -> 15075.305 | D37: =$B$25/C37 -> 0.14811833 | E37: Illustrative sensitivity; parcel model required
A38: 0.5 | B38: 0.5 | C38: =$B$24*A38*B38 -> 21536.149 | D38: =$B$25/C38 -> 0.10368283 | E38: Illustrative sensitivity; parcel model required
A39: 0.5 | B39: 0.65 | C39: =$B$24*A39*B39 -> 27996.994 | D39: =$B$25/C39 -> 0.079756026 | E39: Illustrative sensitivity; parcel model required

Sheet Resource_Royalty
A1: 1% National Resource Royalty - Extraction from U.S. Soil
A3: Covered scope | B3: 2024 base ($B) | C3: Rate | D3: Revenue ($B) | E3: Model status | F3: Notes | G3: Source
A4: Mining, quarrying, oil and gas extraction | B4: 706.4 | C4: 0.01 | D4: =B4*C4 -> 7.064 | E4: Core | F4: Covers oil, natural gas, coal, rare earths, precious/base metals, industrial minerals, quarrying, uranium, and peat where captured in NAICS 21 gross output. | G4: https://fred.stlouisfed.org/series/GOM
A5: Forestry and logging proxy | B5: 46.702 | C5: 0.01 | D5: =B5*C5 -> 0.46702 | E5: Conservative proxy | F5: Uses 2024 real GDP for forestry, fishing and related activities because a clean national forestry-only gross-output series was not available in the model. Replace with BEA forestry/logging gross receipts when available. | G5: https://fred.stlouisfed.org/series/USFRSTFISHRGSP
A6: Core royalty including forestry | B6: =SUM(B4:B5) -> 753.102 | D6: =SUM(D4:D5) -> 7.53102
A8: The royalty is assessed on gross extraction sales/output before downstream refining or manufacturing. Small-producer relief may be appropriated separately, but the royalty itself remains a national return on removed natural wealth.

Sheet Deficit_Views
A1: Expanded Revenue, Cost Discipline, Resident Contributor, and National Continuity Budget - Average Mature Year (v32)
A2: Adds the Offshore Capital Export Duty with a full U.S.-company foreign-expansion carveout, plus High-Wealth Withholding and Compliance Recovery.
A3: TABLE 0 - OLD MODEL BENCHMARK (FY2024)
A4: Line | B4: Amount ($B) | C4: Notes
A5: Current federal receipts | B5: =2024_Basis_Control!B8 -> 4919 | C5: Unified federal benchmark
A6: Current federal outlays | B6: =2024_Basis_Control!B9 -> 6752 | C6: Unified federal benchmark
A7: Current unified federal balance | B7: =B5-B6 -> -1833 | C7: Receipts less outlays
A8: Current OASDI income | B8: =2024_Basis_Control!B10 -> 1418 | C8: Includes current-law trust interest
A9: Current OASDI cost | B9: =2024_Basis_Control!B11 -> 1485 | C9: Annual obligation
A10: Current OASDI balance | B10: =B8-B9 -> -67 | C10: Income less cost
A11: Current national health expenditure | B11: =2024_Basis_Control!B12 -> 5300 | C11: National cost benchmark
A13: TABLE 1 - GENERAL GOVERNMENT FUNDING
A14: Line | B14: Amount ($B) | C14: Notes
A15: Unrestricted General Treasury revenue | B15: =Tax_Revenue_2024!D24 -> 107.4 | C15: Excludes dedicated Citizen Data Royalty
A16: Citizen Data Royalty collection | B16: =Tax_Revenue_2024!D14 -> 73.959598 | C16: Externally collected through General Government
A17: Gross General-administered revenue | B17: =B15+B16 -> 181.3596 | C17: Treasury plus dedicated royalty
A18: Ordinary federal outlays | B18: =2024_Basis_Control!B9-2024_Basis_Control!B11-2024_Basis_Control!B13-Cost_Savings_Program!B27 -> 3460 | C18: FY2024 ordinary outlays less OASDI, current federal healthcare, and $164B mature-year cost savings
A19: Federal health sponsor transfer | B19: =2024_Basis_Control!B13 -> 1643 | C19: Internal transfer into Healthcare ledger
A20: Federal HSA supplement | B20: =Healthcare_3_5_5!D8 -> 281.19657 | C20: Internal transfer into Healthcare ledger
A21: Citizen Wealth Fund transfer | B21: =B16 -> 73.959598 | C21: Equal to Citizen Data Royalty collection
A22: Small Business Surge Reserve | B22: 10 | C22: Standing General Government reserve active in ordinary years
A23: General Government balance before SS support | B23: =B17-SUM(B18:B22) -> -5286.7966
A24: Potential Treasury transfer to close SS gap | B24: =MAX(0,-SS_Hybrid_2024!D13) -> 161.42221 | C24: Memo only; not included in row 23
A26: TABLE 2 - NATIONAL HEALTHCARE FUNDING
A27: Line | B27: Amount ($B) | C27: Notes
A28: Total external healthcare funding | B28: =Healthcare_3_5_5!D19 -> 4604.5095 | C28: Includes federal internal transfers on this ledger
A29: National health expenditure at 20% savings | B29: =Healthcare_3_5_5!D6 -> 4240 | C29: Average mature-year cost target
A30: Healthcare balance | B30: =B28-B29 -> 364.50949 | C30: Positive = dedicated reserve
A31: Internal NHDC/public-hospital margins
A32: Optional state supplements and transition capital | B32: 0 | C32: Outside the national breakeven
A34: TABLE 3 - SOCIAL SECURITY FUNDING
A35: Line | B35: Amount ($B) | C35: Notes
A36: Total dedicated SS funding | B36: =SS_Hybrid_2024!D12+SS_Hybrid_2024!D14+12+National_Continuity!B24 -> 1593.6655 | C36: Citizen + employer + mature NLA + protected trust return + RCN increment + NCC amount needed for breakeven
A37: OASDI cost target | B37: =SS_Hybrid_2024!D5-SS_Hybrid_2024!D15-6 -> 1461 | C37: Annual obligation
A38: Social Security balance | B38: =B36-B37 -> 132.66554
A39: General support can close row 38 without changing the consolidated result.
A41: TABLE 4 - CONSOLIDATED REPLACEMENT RESULT
A42: Line | B42: Amount ($B) | C42: Notes
A43: General Government balance | B43: =37.1560610633821+(Tax_Revenue_2024!D33-5429.13123619) -> 318.95606 | C43: General Government balance including federal SSI savings; before any residual SS backstop
A44: Healthcare balance | B44: =364.50949205+12 -> 376.50949 | C44: Healthcare is independent; reserve and residual public-capital allocations remain within its ledger
A45: Social Security balance | B45: =Budget_0_4_10!D16 -> 0 | C45: Balanced after RCN effects and NCC transfer
A46: Consolidated replacement balance | B46: =Budget_0_4_10!D23 -> 1079.531 | C46: Year 10 maturity result with the NLA ramp modeled from startup
A47: Improvement vs current unified federal deficit | B47: =B46-(-1833) -> 2912.531 | C47: Directional comparison; channel scope differs
A48: NCC transfer to Social Security | B48: =National_Continuity!D24 -> 181.22434 | C48: Year 10 NCC contribution routed to Social Security
A49: General balance after SS support | B49: =B43 -> 318.95606
A50: Consolidated check after SS support | B50: =Budget_0_4_10!D23 -> 1079.531 | C50: Consolidated check after NCC and internal allocations
A52: TABLE 5 - REVENUE PRESENTATION CONTROL
A53: Line
A54: Total Government Revenue | B54: =Total_Government_Revenue!B24 -> 9102.6934 | C54: Year 10 total, including dedicated receipts and gross NCC once
A55: Operating General Treasury Revenue | B55: =Total_Government_Revenue!B26 -> 3391.7622 | C55: Excludes dedicated funds
A56: Citizen Wealth Fund transfer | B56: =Tax_Revenue_2024!D14 -> 73.959598 | C56: Expense in consolidated budget; does not erase the royalty from Total Government Revenue
A57: TABLE 6 - NCC AND INDEPENDENT HEALTHCARE WATERFALL
A58: Line | B58: Amount ($B) | C58: Notes
A59: Gross National Continuity Contribution | B59: =National_Continuity!D22 -> 559.2898 | C59: 0.73% of covered enterprise valuation
A60: NCC transfer to Social Security | B60: =National_Continuity!D24 -> 181.22434 | C60: Amount required to reach annual SS breakeven
A61: NCC residual to NIRF | B61: =National_Continuity!D26 -> 378.06546 | C61: All remaining NCC proceeds
A62: Residual Treasury support to Social Security | B62: =National_Continuity!D27 -> 0 | C62: Zero in central mature-year case
A63: Healthcare reserve floor | B63: 120 | C63: Protected healthcare reserve
A64: Healthcare surplus above reserve | B64: 244.50949 | C64: No routine transfer to Social Security
A65: Healthcare residual to NIRF | B65: =National_Continuity!D32 -> 122.25475 | C65: 50% after approved healthcare R&D/capacity
A66: Healthcare residual to Citizen Wealth Fund | B66: =National_Continuity!D33 -> 122.25475 | C66: 50% after approved healthcare R&D/capacity
A67: Year 0 strict Treasury balance | B67: =National_Continuity!D34 -> 37.156061 | C67: Includes federal SSI saving
A68: Year 10 consolidated replacement surplus | B68: =Budget_0_4_10!D23 -> 1079.531 | C68: Includes external NCC revenue once
A70: Central covered enterprise valuation | B70: =National_Continuity!B6 -> 68000 | C70: $B studied central assessable base; linked to National_Continuity

Sheet Reclassified_Outlays
A1: Consolidated Reconciliation | Year 10 Mature Budget
A2: The reconciliation sums each ledger balance and each external protected-capital receipt once. Internal transfers are excluded.
A3: Line | B3: Amount ($B) | C3: Treatment
A4: General Government balance | B4: =Deficit_Views!B43 -> 318.95606 | C4: External General Government ledger result
A5: Healthcare balance | B5: =Deficit_Views!B44 -> 376.50949 | C5: Independent healthcare ledger result
A6: Social Security ending balance | B6: =Deficit_Views!B45 -> 0 | C6: After Resident Contributor receipts and NCC transfer
A7: NCC residual to NIRF | B7: =National_Continuity!D26 -> 378.06546 | C7: External NCC revenue retained as protected NIRF principal
A8: Spectrum NIRF capital receipt | B8: =6 -> 6 | C8: External spectrum receipt retained as protected NIRF principal
A9: Calculated consolidated replacement balance | B9: =SUM(B4:B8) -> 1079.531 | C9: No internal transfer counted twice
A10: Published consolidated replacement balance | B10: =Deficit_Views!B46 -> 1079.531 | C10: Headline result
A11: Must equal zero | B11: =B9-B10 -> 0 | C11: Publication control

Sheet Debt_Flywheel
A1: Deferred Module - Debt Flywheel (v21)
A2: Not included in the average mature replacement-year headline.
A4: Reason deferred | B4: The funding model must first close its annual consolidated gap before debt retirement or interest-savings feedback can be modeled as a benefit.
A5: Current headline balance | B5: =Deficit_Views!B43 -> 318.95606
A6: Status | B6: Deferred until the base funding gap is closed
A8: This worksheet is retained for the later multi-year model. It contributes zero to the v21 active average-year headline.

Sheet Post_Term_Results
A1: Deferred Module - Multi-Year and Post-Term Results (v21)
A2: Not included in the average mature replacement-year headline.
A4: Measure | B4: Value | C4: Status | D4: Notes
A5: Annual consolidated replacement balance | B5: =Deficit_Views!B43 -> 318.95606 | C5: Active baseline | D5: Links to Deficit_Views
A6: Debt trajectory | B6: 0 | C6: Deferred | D6: Requires a closed annual gap and explicit borrowing assumptions
A7: Interest flywheel | B7: 0 | C7: Deferred | D7: Not credited to the headline
A8: Transition costs | B8: 0 | C8: Out of scope | D8: Average mature-year model only
A9: General Policy Book initiatives | B9: 0 | C9: Out of scope | D9: Costed later
A11: This sheet prevents multi-year effects from being confused with the steady-state replacement comparison.

Sheet Replacement_Summary
A1: Current System to Fully Inclusive Studied Mature Replacement Year - v34
A2: All Policy Book revenue methods are now included in the budget summary. Former placeholders have studied central estimates with ranges and sources. LVT is unchanged.
A4: Metric | B4: Old model / FY2024 benchmark ($B) | C4: New replacement model ($B) | D4: Change ($B) | E4: Interpretation | F4: Scope note
A5: Federal / General Government balance | B5: -1833 | C5: =Deficit_Views!B43 -> 318.95606 | D5: =C5-B5 -> 2151.9561 | E5: General Government balance before any residual Social Security backstop | F5: Citizen Data Royalty collection and CWF transfer net to zero
A6: Social Security annual balance | B6: -67 | C6: =Deficit_Views!B45 -> 0 | D6: =C6-B6 -> 67 | E6: Social Security ending balance after Resident Contributor and NCC funding | F6: Mature NLA and trust assumptions unchanged
A7: National healthcare annual cost | B7: 5300 | C7: =Healthcare_3_5_5!D6 -> 4240 | D7: =C7-B7 -> -1060 | E7: 20% modeled structural savings | F7: Cost rather than budget balance
A8: Healthcare dedicated balance | B8: 0 | C8: =Deficit_Views!B44 -> 376.50949 | D8: =C8-B8 -> 376.50949 | E8: Independent healthcare ledger balance including international licensing | F8: Internal provider margins excluded
A9: Consolidated replacement balance | B9: -1833 | C9: =Deficit_Views!B46 -> 1079.531 | D9: =C9-B9 -> 2912.531 | E9: System-wide recurring result | F9: All scoped active mechanisms included
A11: Headline Inputs and Outputs
A12: Expanded liquid personal income base | C12: =Liquid_Income_Base!B16 -> 20470.758 | E12: Income taxed once when liquid/available
A13: Unrestricted General Treasury revenue | C13: =Tax_Revenue_2024!D33 -> 5710.9312 | E13: Available for ordinary General Government operations
A14: Citizen Data Royalty collection | C14: =Tax_Revenue_2024!D14 -> 73.959598 | E14: Dedicated external collection
A15: Citizen Wealth Fund transfer | C15: =-Tax_Revenue_2024!D35 -> -73.959598 | E15: Equal dedicated transfer to Citizen Wealth Fund
A16: Gross General-administered collections | C16: =Tax_Revenue_2024!D34 -> 5784.8908 | E16: Operating Treasury plus Citizen Data Royalty collection
A17: Luxury Tax revenue | C17: =Tax_Revenue_2024!D13 -> 12.06373 | E17: Flat 5% General Treasury revenue
A18: General Government balance | C18: =Deficit_Views!B43 -> 318.95606 | E18: Before SS support
A19: Healthcare balance | C19: =Deficit_Views!B44 -> 376.50949 | E19: Independent healthcare ledger balance
A20: Social Security balance | C20: =Deficit_Views!B45 -> 0 | E20: Balanced after dedicated funding and NCC transfer
A21: Consolidated replacement balance
A23: Active Policy Inputs in the Headline
A24: Individual income tax | B24: 10% expanded liquid base | C24: =Tax_Revenue_2024!D4 -> 2047.0758 | D24: ACTIVE | E24: Pensions, annuities, royalties, legal/misc cash, foreign cash, data licensing
A25: Estate and trust distribution tax | B25: 3% | C25: =Tax_Revenue_2024!D6 -> 1.5033059 | D25: ACTIVE | E25: Positive distributions
A26: Entity/transaction anti-deferral tax | B26: 10% | C26: =Tax_Revenue_2024!D7 -> 28.270996 | D26: ACTIVE | E26: Form 4797, deferred like-kind gain, positive REMIC
A27: Outsourcing Penalty | B27: 10% | C27: =Tax_Revenue_2024!D9 -> 142.92019 | D27: ACTIVE | E27: Related-party manufacturing-import proxy for >50% outsourcing
A28: Fair Profit Tax | B28: PolicyBook calculator | C28: =Tax_Revenue_2024!D10 -> 3.3070532 | D28: ACTIVE | E28: Original 2024 market screening study
A29: Loan Scumming taxes | B29: 5% payoff + 10% audit | C29: =Tax_Revenue_2024!D11 -> 7.95 | D29: ACTIVE | E29: Asset-backed borrowing used to avoid realization
A30: Protectorate Fee | B30: 1% | C30: =Tax_Revenue_2024!D12 -> 151.4038 | D30: ACTIVE | E30: 77-country legacy expenditure base
A31: Flat Luxury Tax | B31: 5% | C31: =Tax_Revenue_2024!D13 -> 12.06373 | D31: ACTIVE | E31: Personal luxury goods, luxury vehicles, yachts, and business jets
A32: Citizen Data Royalty | B32: 30% | C32: =Tax_Revenue_2024!D14 -> 73.959598 | D32: ACTIVE / CWF | E32: Data-market base with overlap deductions
A33: Federalized Land Value Tax | B33: Full scenario | C33: =Tax_Revenue_2024!D16 -> 2232.929 | D33: ACTIVE | E33: Primary home exempt; full revenue booked
A34: Retained current-law federal receipts | B34: Aggregate | C34: =Tax_Revenue_2024!D19 -> 253 | D34: ACTIVE | E34: Receipt classes not repealed
A35: Energy export excise | B35: 5% deficit-year | C35: =Tax_Revenue_2024!D18 -> 16.84285 | D35: ACTIVE | E35: Automatic 5% when prior-year consolidated balance is negative
A36: Employer equity compensation surtax | B36: 9% aggregate | C36: =Tax_Revenue_2024!D8 -> 33.003 | D36: ACTIVE | E36: Approved marginal schedule through $1M
A37: Employer SS on capital wages | B37: 3% | C37: =Equity_Compensation!D6 -> 11.001 | D37: ACTIVE | E37: Equity compensation covered at fair value
A38: NHDC mature international export margin
A39: Small Business Surge Reserve | B39: Standing reserve | C39: =-Deficit_Views!B22 -> -10 | D39: ACTIVE COST | E39: General Government obligation
A40: Idle Wealth Levy | B40: 1% central certified base | C40: =Tax_Revenue_2024!D20 -> 47.714505 | D40: ACTIVE | E40: Concentrated nonproductive financial reserves; managers withhold for clients; no cross-tier credit
A41: Total Government Revenue | B41: Presentation control | C41: =Total_Government_Revenue!B19 -> 6 | D41: ACTIVE VIEW | E41: Includes dedicated CWF royalty once; excludes private HSAs
A42: Offshore Capital Export Duty | B42: 10% central behavioral score | C42: =Offshore_Capital_Duty!F12 -> 19.2 | D42: ACTIVE | E42: Passive outbound capital; bona fide U.S. foreign expansion carved out
A43: High-Wealth Withholding Recovery | B43: Collection mechanism | C43: =High_Wealth_Compliance!F9 -> 38 | D43: ACTIVE | E43: Existing liabilities collected through controlled intermediaries
A44: Cross-policy overlap adjustment | B44: Anti-double-counting | C44: -4 | D44: ACTIVE ADJUSTMENT | E44: Offsets overlapping offshore/compliance collections
A45: Revised consolidated surplus | B45: After additions | C45: =Budget_0_4_10!D23 -> 1079.531 | D45: ACTIVE VIEW | E45: Three-ledger consolidated result
A46: Total mature-year cost savings | B46: Central/midpoint policy case | C46: =Cost_Savings_Program!B27 -> 164 | D46: ACTIVE SAVINGS | E46: Integrity, procurement, grants, workforce, credit, and military right-to-repair savings after overlap removal
A47: Revised ordinary federal outlays | B47: After mature-year savings | C47: =Deficit_Views!B18 -> 3460 | D47: ACTIVE VIEW | E47: Ordinary General Government outlays after cost reduction
A48: Revised consolidated surplus | B48: After full cost-savings program | C48: =Budget_0_4_10!D23 -> 1079.531 | D48: ACTIVE VIEW | E48: Average mature replacement-year result
A49: Social Security projection finding | B49: Year 0 | C49: =Budget_0_4_10!B13 -> 205.67979 | D49: ACTIVE ANALYSIS | E49: Gap with Year 0 startup NLA
A50: Social Security projection finding | B50: Year 4 | C50: =Budget_0_4_10!C13 -> 217.89468 | D50: ACTIVE ANALYSIS | E50: Gap with Year 4 full-term NLA growth
A51: Social Security projection finding | B51: Year 10 | C51: =Budget_0_4_10!D13 -> 181.22434 | D51: ACTIVE ANALYSIS | E51: Gap with Year 10 mature NLA
A52: Trust drawdown warning | B52: Without Treasury stabilization | C52: =SS_Year_0_4_10!D22 -> 1720.4774 | D52: RISK | E52: Trust corpus approaches depletion before Year 10
A53: Protected Social Security trust floor | B53: $2.7T | C53: 2700 | D53: ADOPTED | E53: Treasury backstop prevents reserve corpus from falling below the floor
A54: Protected healthcare reserve floor | B54: $120B | C54: 120 | D54: ADOPTED | E54: Pandemic and disaster override applies
A55: Healthcare excess above reserve | B55: Year 0 | C55: =Budget_0_4_10!B13 -> 205.67979 | D55: ACTIVE | E55: First supports Social Security
A56: Healthcare transfer to Social Security | B56: Year 0 | C56: =Budget_0_4_10!B15 -> 205.67979 | D56: ACTIVE | E56: Closes dedicated gap before Treasury support
A57: Residual Treasury support | B57: Year 0 | C57: =Budget_0_4_10!B17 -> 290.72021 | D57: ACTIVE | E57: Only remaining amount needed to preserve trust floor
A58: NIRF allocation from residual healthcare profit | B58: Year 0 | C58: =Deficit_Views!B64 -> 244.50949 | D58: ACTIVE | E58: 50% after SS is balanced
A59: CWF allocation from residual healthcare profit | B59: Year 0 | C59: =Deficit_Views!B65 -> 122.25475 | D59: ACTIVE | E59: 50% after SS is balanced
A60: Citizen-only SS incremental contributions | B60: Year 0 | C60: =Noncitizen_SS_Model!B17 -> 52.407964 | D60: ACTIVE | E60: 7% employee and 7% employer less existing 3%/3% baseline
A61: Noncitizen OASDI benefit saving | B61: Year 0 | C61: =Noncitizen_SS_Model!B21 -> 18 | D61: MODELED | E61: Central estimate; explicit uncertainty
A62: Federal SSI saving | B62: Year 0 | C62: =Noncitizen_SS_Model!B22 -> 2.22139 | D62: VERIFIED FLOW | E62: General Government saving, not OASDI trust income
A63: Revised SS gap before healthcare | B63: Year 0 | C63: =Noncitizen_SS_Model!B34 -> 217.67979 | D63: ACTIVE | E63: After immigration-policy effects only
A64: Healthcare transfer to SS | B64: Year 0 | C64: =Noncitizen_SS_Model!B35 -> 217.67979 | D64: ACTIVE | E64: First priority above $120B reserve
A65: Residual healthcare profit | B65: Year 0 | C65: =Noncitizen_SS_Model!B37 -> 26.829705 | D65: ACTIVE | E65: Split 50/50 between NIRF and CWF
A66: Revised consolidated surplus | B66: Year 0 | C66: =Noncitizen_SS_Model!B40 -> 183.98577 | D66: ACTIVE | E66: Includes OASDI, contribution, and SSI effects
A67: National Continuity Contribution rate | B67: Flat annual enterprise-value levy | C67: 0.0073 | D67: ADOPTED | E67: Applies above $1M at annual registration
A68: Central covered enterprise valuation | B68: Modeled assessable base | C68: =National_Continuity!B6 -> 68000 | D68: MODELED | E68: Linked to validated National_Continuity central base
A69: Gross NCC revenue | B69: Year 0 | C69: =Budget_0_4_10!B14 -> 496.4 | D69: ACTIVE | E69: External dedicated revenue
A70: NCC transfer to Social Security | B70: Year 0 | C70: =Budget_0_4_10!B15 -> 205.67979 | D70: ACTIVE | E70: Closes annual SS gap
A71: NCC residual to NIRF | B71: Year 0 | C71: =Budget_0_4_10!B17 -> 290.72021 | D71: ACTIVE | E71: After SS breakeven
A72: Healthcare transfer to Social Security | B72: Year 0 | C72: 0 | D72: REMOVED | E72: NHDC fully independent
A73: Healthcare residual to NIRF | B73: Year 0 | C73: =National_Continuity!B32 -> 122.25475 | D73: ACTIVE | E73: 50% after reserve and approved healthcare needs
A74: Healthcare residual to CWF | B74: Year 0 | C74: =National_Continuity!B33 -> 122.25475 | D74: ACTIVE | E74: 50% after reserve and approved healthcare needs
A75: Carbon Tax | B75: Studied central | C75: 107.4 | D75: ACTIVE | E75: $25/t, 10% mature erosion | F75: Revenue_Validation
A76: Spectrum stewardship gross | B76: Studied central | C76: 12 | D76: ACTIVE | E76: Treasury + NIRF + administration | F76: Revenue_Validation
A77: Federal enterprise data services net | B77: Studied central | C77: 2 | D77: ACTIVE | E77: Premium services over free public data | F77: Revenue_Validation
A78: National lab patent marketplace net | B78: Studied central | C78: 0.4 | D78: ACTIVE | E78: Licenses, royalties, exclusivity auctions | F78: Revenue_Validation
A79: Industrial campus leases/services net | B79: Studied central | C79: 10 | D79: ACTIVE | E79: Ground leases, utilities, testing, royalties | F79: Revenue_Validation
A80: Pipeline capacity auctions net | B80: Studied central | C80: 3.5 | D80: ACTIVE | E80: Corridor capacity and ROW rents | F80: Revenue_Validation
A81: NHDC international licenses | B81: Studied central | C81: 12 | D81: ACTIVE | E81: Dedicated healthcare earnings | F81: Revenue_Validation
A82: NLA institutional/international | B82: Studied central | C82: 12 | D82: ACTIVE | E82: Dedicated Social Security earnings | F82: Revenue_Validation
A83: Commercial space infrastructure net | B83: Studied central | C83: 3 | D83: ACTIVE | E83: Service revenue net of operations | F83: Revenue_Validation
A84: Patent troll penalties | B84: Studied central | C84: 0.5 | D84: ACTIVE | E84: Deterrence-based; not relied upon | F84: Revenue_Validation
A85: NIRF distributable return | B85: Studied mature | C85: 150 | D85: ACTIVE | E85: Protected principal retained | F85: Revenue_Validation
A86: National Continuity covered valuation | B86: Studied central | C86: 68000 | D86: ACTIVE | E86: $B; Federal Reserve basis | F86: Revenue_Validation
A87: Consolidated replacement balance | B87: Fully inclusive | C87: =Budget_0_4_10!D23 -> 1079.531 | D87: ACTIVE | E87: All revenue methods included | F87: Deficit_Views

Sheet Sources
A1: Sources - Plain URLs Used
A3: Topic | B3: Source | C3: URL | D3: Notes
A4: Personal income | B4: FRED/BEA | C4: https://fred.stlouisfed.org/series/A065RC1A027NBEA | D4: 2024 and modern annual values
A5: GNI | B5: World Bank/FRED | C5: https://fred.stlouisfed.org/series/MKTGNIUSA646NWDB | D5: 2024 and modern values
A6: Wages/salaries | B6: FRED/BEA | C6: https://fred.stlouisfed.org/series/BA06RC1A027NBEA | D6: 2024 payroll base
A7: Corporate profits | B7: FRED/BEA | C7: https://fred.stlouisfed.org/series/A053RC1A027NBEA | D7: 2024 and modern profits
A8: Federal budget | B8: CBO | C8: https://www.cbo.gov/publication/60843/html | D8: FY2024 receipts/outlays
A9: Social Security | B9: SSA | C9: https://www.ssa.gov/oact/TR/2025/III_A_cyoper.html | D9: 2024 OASDI cost/income
A10: Healthcare | B10: CMS | C10: https://www.cms.gov/data-research/statistics-trends-and-reports/national-health-expenditure-data/nhe-fact-sheet | D10: 2024 NHE
A11: Property taxes | B11: Census/NAHB | C11: https://eyeonhousing.org/tag/state-and-local-tax-revenue/ | D11: 2024 property-tax benchmark
A12: Farmland values | B12: USDA | C12: https://www.nass.usda.gov/Publications/Todays_Reports/reports/land0824.pdf | D12: 2024 farm real estate values
A13: Household real estate | B13: Fed/FRED | C13: https://fred.stlouisfed.org/series/HNOREMV | D13: Residential real estate scale
A14: Corporate real estate | B14: Fed/FRED | C14: https://fred.stlouisfed.org/series/BOGZ1LM105035005A | D14: Corporate real estate scale
... A78: High-income evasion research | B78: IRS SOI research | C78: Offshore and pass-through evasion concentrated at the top | D78: https://www.irs.gov/pub/irs-soi/23rptaxevasiontopincomedist.pdf

Sheet QA_Checks
A1: QA Checks - v35 Publication Ready
A3: Check | B3: Expected | C3: Result | D3: Status
A4: Expanded liquid base ties | B4: 20470.758 | C4: =Liquid_Income_Base!B16 -> 20470.758 | D4: =IF(ABS(B4-C4)<0.001,"PASS","CHECK") -> PASS
A5: Citizen Data Royalty base ties | B5: 246.53199 | C5: =Citizen_Data_Royalty!H13 -> 246.53199 | D5: =IF(ABS(B5-C5)<0.001,"PASS","CHECK") -> PASS
A6: Citizen Data Royalty collection ties | B6: 73.959598 | C6: =Citizen_Data_Royalty!J13 -> 73.959598 | D6: =IF(ABS(B6-C6)<0.001,"PASS","CHECK") -> PASS
A7: CWF transfer equals Data Royalty | B7: 0 | C7: =Deficit_Views!B56-Tax_Revenue_2024!D14 -> 0 | D7: =IF(ABS(B7-C7)<0.001,"PASS","CHECK") -> PASS
A8: Luxury tax base ties | B8: 241.2746 | C8: =Luxury_Tax!D10 -> 241.2746 | D8: =IF(ABS(B8-C8)<0.001,"PASS","CHECK") -> PASS
A9: Luxury tax revenue ties | B9: 12.06373 | C9: =Luxury_Tax!F10 -> 12.06373 | D9: =IF(ABS(B9-C9)<0.001,"PASS","CHECK") -> PASS
A10: Operating Treasury subtotal excludes dedicated Data Royalty and sin surtax | B10: 0 | C10: =Tax_Revenue_2024!D33-(SUM(Tax_Revenue_2024!D4:D13)+SUM(Tax_Revenue_2024!D16:D23)+SUM(Tax_Revenue_2024!D24:D32)) -> 0 | D10: =IF(ABS(B10-C10)<0.001,"PASS","CHECK") -> PASS
A11: Gross administered collection ties | B11: 0 | C11: =Deficit_Views!B17-(Deficit_Views!B15+Deficit_Views!B16) -> 0 | D11: =IF(ABS(B11-C11)<0.001,"PASS","CHECK") -> PASS
A12: General Government balance ties | B12: 0 | C12: =Deficit_Views!B23-(Deficit_Views!B17-SUM(Deficit_Views!B18:B22)) -> 0 | D12: =IF(ABS(B12-C12)<0.001,"PASS","CHECK") -> PASS
A13: Healthcare balance ties | B13: 0 | C13: =Deficit_Views!B30-(Deficit_Views!B28-Deficit_Views!B29) -> 0 | D13: =IF(ABS(B13-C13)<0.001,"PASS","CHECK") -> PASS
A14: Social Security balance ties | B14: 0 | C14: =Deficit_Views!B38-(Deficit_Views!B36-Deficit_Views!B37) -> 0 | D14: =IF(ABS(B14-C14)<0.001,"PASS","CHECK") -> PASS
A15: Consolidated Year 10 balance ties to ledgers and NCC residual | B15: 0 | C15: =Deficit_Views!B46-(Deficit_Views!B43+Deficit_Views!B44+Deficit_Views!B45+National_Continuity!D26+6) -> 0 | D15: =IF(ABS(B15-C15)<0.001,"PASS","CHECK") -> PASS
A16: Reclassified ledger reconciliation | B16: 0 | C16: =Reclassified_Outlays!B11 -> 0 | D16: =IF(ABS(B16-C16)<0.001,"PASS","CHECK") -> PASS
A17: Healthcare internal margins excluded | B17: 113 | C17: =Healthcare_3_5_5!D23 -> 113 | D17: =IF(ABS(B17-C17)<0.001,"PASS","CHECK") -> PASS
A18: Small-business surge reserve active | B18: 10 | C18: =Deficit_Views!B22 -> 10 | D18: =IF(ABS(B18-C18)<0.001,"PASS","CHECK") -> PASS
A19: SS support does not change consolidation | B19: 0 | C19: =Deficit_Views!B50-Deficit_Views!B46 -> 0 | D19: =IF(ABS(B19-C19)<0.001,"PASS","CHECK") -> PASS
A20: LVT headline equals full scenario input | B20: 2232.929 | C20: =Tax_Revenue_2024!D16 -> 2232.929 | D20: =IF(ABS(B20-C20)<0.001,"PASS","CHECK") -> PASS
A21: Equity tranche above $1M remains set at adoption | B21: 1 | C21: =IF(Equity_Compensation!B16="Set at adoption",1,0) -> 1 | D21: =IF(ABS(B21-C21)<0.001,"PASS","CHECK") -> PASS
A22: Equity aggregate active rate | B22: 0.09 | C22: =Equity_Compensation!B18 -> 0.09 | D22: =IF(ABS(B22-C22)<0.001,"PASS","CHECK") -> PASS
A23: Retained current-law receipts active | B23: 253 | C23: =Tax_Revenue_2024!D19 -> 253 | D23: =IF(ABS(B23-C23)<0.001,"PASS","CHECK") -> PASS
A24: Outsourcing penalty active | B24: 142.92019 | C24: =Tax_Revenue_2024!D9 -> 142.92019 | D24: =IF(ABS(B24-C24)<0.001,"PASS","CHECK") -> PASS
A25: Fair Profit Tax active | B25: 3.3070532 | C25: =Tax_Revenue_2024!D10 -> 3.3070532 | D25: =IF(ABS(B25-C25)<0.001,"PASS","CHECK") -> PASS
A26: Loan Scumming active | B26: 7.95 | C26: =Tax_Revenue_2024!D11 -> 7.95 | D26: =IF(ABS(B26-C26)<0.001,"PASS","CHECK") -> PASS
A27: Protectorate Fee active | B27: 151.4038 | C27: =Tax_Revenue_2024!D12 -> 151.4038 | D27: =IF(ABS(B27-C27)<0.001,"PASS","CHECK") -> PASS
A28: Year 0 NLA profit uses startup case | B28: 0 | C28: =Budget_0_4_10!B5-NLA_Model!E21 -> 0 | D28: =IF(ABS(B28-C28)<0.001,"PASS","CHECK") -> PASS
A29: Mature-year cost savings booked | B29: 164 | C29: =Cost_Savings_Program!B27 -> 164 | D29: =IF(ABS(B29-C29)<0.001,"PASS","CHECK") -> PASS
A30: Year 10 consolidated surplus ties | B30: 1079.531 | C30: =Budget_0_4_10!D23 -> 1079.531 | D30: =IF(ABS(B30-C30)<0.001,"PASS","CHECK") -> PASS
A31: Protected SS trust floor | B31: 2700 | C31: =SS_Trust_Investment!D4 -> 2700 | D31: =IF(ABS(B31-C31)<0.001,"PASS","CHECK") -> PASS
A32: Healthcare reserve floor | B32: 120 | C32: =National_Continuity!B29 -> 120 | D32: =IF(ABS(B32-C32)<0.001,"PASS","CHECK") -> PASS
A33: Year 0 SS ending balance after waterfall | B33: 0 | C33: =SS_Year_0_4_10!B29 -> 0 | D33: =IF(ABS(B33-C33)<0.001,"PASS","CHECK") -> PASS
A34: Citizen-only SS incremental contribution | B34: =Noncitizen_SS_Model!B17 -> 52.407964 | C34: =Noncitizen_SS_Model!B16-Noncitizen_SS_Model!B15 -> 52.407964 | D34: =IF(ABS(B34-C34)<0.001,"PASS","CHECK") -> PASS
A35: Federal SSI saving | B35: =Noncitizen_SS_Model!B22 -> 2.22139 | C35: =319391*579.59*12/1000000000 -> 2.22139 | D35: =IF(ABS(B35-C35)<0.001,"PASS","CHECK") -> PASS
A36: Year 0 Treasury support after immigration policy | B36: 0 | C36: =Noncitizen_SS_Model!B36 -> 0 | D36: =IF(ABS(B36-C36)<0.001,"PASS","CHECK") -> PASS
A37: NCC rate | B37: 0.0073 | C37: =National_Continuity!B7 -> 0.0073 | D37: =IF(ABS(B37-C37)<0.000001,"PASS","CHECK") -> PASS
A38: Year 0 SS balance after NCC | B38: 0 | C38: =SS_Year_0_4_10!B29 -> 0 | D38: =IF(ABS(B38-C38)<0.001,"PASS","CHECK") -> PASS
A39: Year 0 NHDC transfer to SS | B39: 0 | C39: =National_Continuity!B28 -> 0 | D39: =IF(ABS(B39-C39)<0.001,"PASS","CHECK") -> PASS
A40: Year 0 NCC residual to NIRF | B40: =National_Continuity!B26 -> 290.72021 | C40: =MAX(0,National_Continuity!B22-National_Continuity!B24) -> 290.72021 | D40: =IF(ABS(B40-C40)<0.001,"PASS","CHECK") -> PASS
A41: Publication rule: every active QA check must read PASS.
A42: All added revenue net total | B42: =Additional_Revenue!D16 -> 307.8 | C42: =SUM(Additional_Revenue!D5:D15) -> 307.8 | D42: =IF(ABS(B42-C42)<0.001,"PASS","CHECK") -> PASS
A43: NCC studied base cross-reference | B43: =National_Continuity!B6 -> 68000 | C43: =Replacement_Summary!C68 -> 68000 | D43: =IF(ABS(B43-C43)<0.001,"PASS","CHECK") -> PASS
A44: LVT unchanged | B44: 2232.929 | C44: =Tax_Revenue_2024!D16 -> 2232.929 | D44: =IF(ABS(B44-C44)<0.001,"PASS","CHECK") -> PASS
A45: Total Government Revenue reconciliation | B45: =Total_Government_Revenue!B24 -> 9102.6934 | C45: =SUM(Total_Government_Revenue!B5:B19) -> 9102.6934 | D45: =IF(ABS(B45-C45)<0.001,"PASS","CHECK") -> PASS
A46: Operating Treasury reconciliation | B46: =Total_Government_Revenue!B25 -> 5710.9312 | C46: =Tax_Revenue_2024!D33 -> 5710.9312 | D46: =IF(ABS(B46-C46)<0.001,"PASS","CHECK") -> PASS
A47: Consolidated Year 10 balance reconciliation | B47: =Budget_0_4_10!D23 -> 1079.531 | C47: =Deficit_Views!B46 -> 1079.531 | D47: =IF(ABS(B47-C47)<0.001,"PASS","CHECK") -> PASS
A48: Publication rule: every active QA check must read PASS.

Sheet NLA_Model
A1: National Lending Authority - 10% Fixed-Rate Revenue and Profit Model
A3: Loan category | B3: 2024 addressable balance ($B) | C3: Initial share | D3: Central share | E3: Mature share | F3: Central portfolio ($B) | G3: Source | H3: Notes
A4: Home mortgages | B4: 13140 | C4: 0.02 | D4: 0.08 | E4: 0.2 | F4: =B4*D4 -> 1051.2 | G4: https://www.federalreserve.gov/publications/November-2024-Borrowing-by-Businesses-and-Households.htm | H4: NLA mortgages remain exactly 10%; private prime mortgages may be cheaper.
A5: Student loans | B5: 1745 | C5: 0.1 | D5: 0.25 | E5: 0.5 | F5: =B5*D5 -> 436.25 | G5: https://www.federalreserve.gov/publications/November-2024-Borrowing-by-Businesses-and-Households.htm | H5: Includes refinancing and new federal public lending.
A6: Auto loans | B6: 1563 | C6: 0.08 | D6: 0.2 | E6: 0.4 | F6: =B6*D6 -> 312.6 | G6: https://www.federalreserve.gov/publications/November-2024-Borrowing-by-Businesses-and-Households.htm | H6: 1% down payment required.
A7: Other consumer/personal credit | B7: 408 | C7: 0.1 | D7: 0.25 | E7: 0.5 | F7: =B7*D7 -> 102 | G7: https://www.federalreserve.gov/publications/November-2024-Borrowing-by-Businesses-and-Households.htm | H7: Consumer credit less student, auto, and credit-card balances; credit cards excluded from base.
A8: Total addressable / portfolio | B8: =SUM(B4:B7) -> 16856 | F8: =SUM(F4:F7) -> 1902.05
A10: Core pricing and cost assumptions | B10: Rate / Value | C10: Treatment | D10: Policy
A11: Fixed true annual interest rate | B11: 0.1 | C11: Gross interest revenue | D11: Exactly 10%, no more and no less
A12: Funding cost | B12: 0.04 | C12: Expense assumption | D12: Scenario input; public borrowing/funding cost
A13: Net credit loss rate | B13: 0.0125 | C13: Expense assumption | D13: After recoveries and collateral
A14: Servicing and operating cost | B14: 0.0075 | C14: Expense assumption | D14: Underwriting, servicing, collections, systems
A15: Required reserve addition | B15: 0.005 | C15: Retained capital | D15: Not distributable profit
A16: Annual origination turnover | B16: 0.15 | C16: New loan originations / portfolio | D16: Used to estimate applications
A17: Average qualifying loan size ($) | B17: 25000 | C17: Fee-volume assumption | D17: Loans over $1,000 pay $100 application fee
A18: Application fee ($) | B18: 100 | C18: Operating revenue | D18: Only fee; 1% down payment is principal equity, not revenue
A20: Projection point | B20: Portfolio ($B) | C20: Gross interest revenue ($B) | D20: Application fees ($B) | E20: Distributable net profit ($B)
A21: Year 0 startup | B21: =SUMPRODUCT(B4:B7,C4:C7) -> 603.14 | C21: =B21*$B$11 -> 60.314 | D21: =B21*$B$16*($B$18/$B$17) -> 0.361884 | E21: =B21*($B$11-$B$12-$B$13-$B$14-$B$15)+D21 -> 21.471784
A22: Year 4 full-term growth | B22: =F8 -> 1902.05 | C22: =B22*$B$11 -> 190.205 | D22: =B22*$B$16*($B$18/$B$17) -> 1.14123 | E22: =B22*($B$11-$B$12-$B$13-$B$14-$B$15)+D22 -> 67.71298
A23: Year 10 maturity | B23: =SUMPRODUCT(B4:B7,E4:E7) -> 4329.7 | C23: =B23*$B$11 -> 432.97 | D23: =B23*$B$16*($B$18/$B$17) -> 2.59782 | E23: =B23*($B$11-$B$12-$B$13-$B$14-$B$15)+D23 -> 154.13732
A25: Additional NLA portfolio required to close the remaining mature SS gap | B25: Remaining SS gap ($B) | C25: Net earnings yield incl. fees | D25: Additional portfolio ($B) | E25: Conclusion
A26: Mature replacement assumptions | B26: =-SS_Hybrid_2024!D13 -> 161.42221 | C26: =($B$11-$B$12-$B$13-$B$14-$B$15)+($B$16*$B$18/$B$17) -> 0.0356 | D26: =B26/C26 -> 4534.3319 | E26: Additional scale can help, but the mature portfolio does not close the SS gap by itself.
A28: NLA statutory controls: fixed 10% true annual interest; $100 application fee on loans over $1,000; 1% down payment on non-housing loans; no origination points, prepaid-interest fees, dealer markups, mandatory add-ons, buydown fees, obscured compounding/servicing charges, or prepayment penalties. Minimum underwriting, verified income and repayment capacity, loan-type collateral rules, debt-to-income limits, fraud controls, loss reserves, hardship restructuring, and lawful federal collection authority apply. Tax-record access is limited to statutory loan administration and collection with taxpayer-confidentiality safeguards. Civil recovery contractors may locate debtors/assets and serve process, but may not exercise criminal arrest powers.
A30: The fiscal path now uses Year 0 startup profit, Year 4 full-term growth profit, and Year 10 maturity profit. The mature scenario remains the steady-state destination rather than an immediate Year 0 assumption.

Sheet NAIC_Policy
A1: National Auto Insurance Corporation (NAIC) - At-Cost Public Option
A3: Policy line | B3: Treatment | C3: Budget treatment | D3: Notes
A4: Institutional purpose | B4: Bare-bones public auto insurance option | C4: Self-funded insurance corporation | D4: Disciplines private premiums through a low-cost public competitor.
A5: Core coverage | B5: Legally required liability plus basic collision | C5: Claims obligation | D5: No rental reimbursement, roadside assistance, luxury replacement, or bundled extras.
A6: Premium standard | B6: Actuarial expected claims + administration + fraud control + prudent reserves | C6: Operating receipts, not federal tax revenue | D6: The corporation does not seek distributable profit.
A7: Surplus treatment | B7: Retained for solvency, future premium reductions, or policyholder rebates | C7: No transfer to Social Security or Treasury | D7: Prevents insurance reserves from being counted as general revenue.
A8: Loss treatment | B8: Premium adjustments and reserves absorb ordinary volatility | C8: No automatic general-budget charge | D8: Extraordinary catastrophe support requires separate statutory appropriation.
A10: NAIC is distinct from the NLA. The NAIC operates at actuarial cost; the NLA is a fixed-rate public commercial lender that seeks net earnings after expenses and reserves.

Sheet Energy_Export_Excise
A1: 3-5% Energy Export Excise - 2024 Census Export Values (Active Deficit-Year Rate: 5%)
A3: Covered export category | B3: 2024 export value ($B) | C3: Rate | D3: Revenue ($B) | E3: Coverage note | F3: Source
A4: Crude oil | B4: 117.949 | C4: 0.05 | D4: =B4*C4 -> 5.89745 | E4: Export sale value | F4: https://www.census.gov/foreign-trade/Press-Release/ft900/ft900_2412.pdf
A5: Fuel oil | B5: 50.235 | C5: 0.05 | D5: =B5*C5 -> 2.51175 | E5: Refined fuel exports | F5: https://www.census.gov/foreign-trade/Press-Release/ft900/ft900_2412.pdf
A6: Natural gas liquids | B6: 34.922 | C6: 0.05 | D6: =B6*C6 -> 1.7461 | E6: NGL exports | F6: https://www.census.gov/foreign-trade/Press-Release/ft900/ft900_2412.pdf
A7: Natural gas | B7: 34.187 | C7: 0.05 | D7: =B7*C7 -> 1.70935 | E7: Pipeline and LNG end-use category | F7: https://www.census.gov/foreign-trade/Press-Release/ft900/ft900_2412.pdf
A8: Other petroleum products | B8: 77.616 | C8: 0.05 | D8: =B8*C8 -> 3.8808 | E8: Other downstream petroleum exports | F8: https://www.census.gov/foreign-trade/Press-Release/ft900/ft900_2412.pdf
A9: Coal and fuels, other | B9: 10.849 | C9: 0.05 | D9: =B9*C9 -> 0.54245 | E9: Coal and other fuels | F9: https://www.census.gov/foreign-trade/Press-Release/ft900/ft900_2412.pdf
A10: Metallurgical grade coal | B10: 10.255 | C10: 0.05 | D10: =B10*C10 -> 0.51275 | E10: Metallurgical coal exports | F10: https://www.census.gov/foreign-trade/Press-Release/ft900/ft900_2412.pdf
A11: Electric energy | B11: 0.844 | C11: 0.05 | D11: =B11*C11 -> 0.0422 | E11: Exported electricity | F11: https://www.census.gov/foreign-trade/Press-Release/ft900/ft900_2412.pdf
A12: Total covered energy exports | B12: =SUM(B4:B11) -> 336.857 | D12: =SUM(D4:D11) -> 16.84285
A14: The excise applies only to the customs value of covered energy exports. The statutory band remains 3-5%. The active rate is 5% whenever the prior-year consolidated replacement budget records a deficit, and 4% after balance is restored. Imports and domestic sales remain untouched.
A16: Scenario | B16: Rate | C16: Revenue ($B)
A17: 3% statutory floor | B17: 0.03 | C17: =B12*B17 -> 10.10571
A18: Balanced-budget baseline | B18: 0.04 | C18: =$B$12*B18 -> 13.47428
A19: Active deficit-year rate | B19: 0.05 | C19: =$B$12*B19 -> 16.84285

Sheet Anti_Deferral_Tax
A1: Entity-Level Anti-Deferral Tax - Form 4797, Like-Kind Deferral, and REMIC Residuals
A2: Active 10% source-level tax when gains are retained in an entity, trust, partnership, or real-estate structure rather than paid to or solely owned by an individual. Same-year individual distributions receive a dollar-for-dollar credit to prevent double taxation.
A4: Tax base component | B4: 2023 national base ($B) | C4: Rate | D4: Revenue ($B) | E4: Treatment | F4: Source
A5: Form 4797 combined gains, line 7 | B5: 258.98582 | C5: 0.1 | D5: =B5*C5 -> 25.898582 | E5: Transaction-scale proxy for trade-up and business-property gains | F5: IRS Publication 4801, Form 4797 statistics
A6: Deferred gain from like-kind exchanges, Form 8824 line 24 | B6: 23.724133 | C6: 0.1 | D6: =B6*C6 -> 2.3724133 | E6: Deferred gain brought into the source-level base | F6: IRS Publication 4801, Form 8824 statistics
A7: Positive REMIC residual taxable income | B7: 0 | C7: 0.1 | D7: =B7*C7 -> 0 | E7: Negative combined national value floors at zero for active scoring | F7: IRS Publication 4801, Schedule E statistics
A9: Total active anti-deferral base | B9: =SUM(B5:B7) -> 282.70996 | C9: Total active revenue | D9: =SUM(D5:D7) -> 28.270996 | E9: Collected at the transaction/entity source; credited against the same economic income when later distributed to an individual.
A11: Policy construction: the 10% source tax closes indefinite nonrecognition and entity-retention chains without taxing the same dollar twice. It applies when no individual has received or solely owns the gain.

Sheet Outsourcing_Penalty
A1: Outsourcing Penalty - 10% Active Manufacturing Import Proxy
A2: PolicyBook v86 applies an absolute 10% tax to companies outsourcing more than half of manufacturing. The public-data proxy uses 2024 related-party manufacturing imports across NAICS 31-33; firm-level implementation replaces the proxy with the statutory >50% test.
A4: NAICS sector | B4: 2024 related-party imports ($B) | C4: Statutory rate | D4: Modeled revenue ($B) | E4: Coverage | F4: Source | G4: Status
A5: NAICS 31 - Food, textiles, apparel, leather | B5: 69.874829 | C5: 0.1 | D5: =B5*C5 -> 6.9874829 | E5: Manufacturing imports | F5: U.S. Census Related-Party Trade 2024 | G5: ACTIVE PROXY
A6: NAICS 32 - Chemicals, petroleum, plastics, nonmetallic minerals | B6: 373.57097 | C6: 0.1 | D6: =B6*C6 -> 37.357097 | E6: Manufacturing imports | F6: U.S. Census Related-Party Trade 2024 | G6: ACTIVE PROXY
A7: NAICS 33 - Primary/fabricated metals, machinery, computers, transport | B7: 985.75613 | C7: 0.1 | D7: =B7*C7 -> 98.575613 | E7: Manufacturing imports | F7: U.S. Census Related-Party Trade 2024 | G7: ACTIVE PROXY
A9: Total active proxy | B9: =SUM(B5:B7) -> 1429.2019 | C9: =C5 -> 0.1 | D9: =SUM(D5:D7) -> 142.92019 | E9: Affiliated manufacturing imports | F9: Census related-party trade | G9: ACTIVE
A11: Implementation rule: aggregate the affiliated corporate group and its controlled contractors over a rolling three-year period. When foreign manufacturing exceeds 50%, tax the customs value of covered foreign-manufactured goods and components entering the United States. The proxy is deliberately active until firm-level customs reports become available.

Sheet Fair_Profit_Study
A1: Fair Profit Tax - Original 2024 Market Screening Study
A2: Active study of mass-produced physical goods above $100. A product enters the tax base only when price exceeds 10x materials, labor, and amortized R&D cost. Art, boutique/custom production, software, and SaaS are excluded. The PolicyBook calculator rate is 0.5 percentage point for each completed multiple above 10x, capped at 50%.
A4: Market category | B4: 2024 U.S. sales ($B) | C4: Mass-produced eligible share | D4: Sales above $100 share | E4: Share exceeding 10x fully loaded cost | F4: Average qualifying multiple | G4: Calculator rate | H4: Qualifying sales base ($B) | I4: Fair Profit revenue ($B) | J4: Source / construction | K4: Status
A5: Prescription drugs | B5: 467 | C5: 1 | D5: 0.75 | E5: 0.18 | F5: 18 | G5: =IF(F5>10,MIN(50%,INT(F5-10)*0.5%),0) -> 0.04 | H5: =B5*C5*D5*E5 -> 63.045 | I5: =H5*G5 -> 2.5218 | J5: CMS 2024 retail prescription-drug spending; original eligibility and markup screening assumptions | K5: ACTIVE STUDY
A6: Other health and medical goods | B6: 65.989 | C6: 0.9 | D6: 0.35 | E6: 0.12 | F6: 16 | G6: =IF(F6>10,MIN(50%,INT(F6-10)*0.5%),0) -> 0.03 | H6: =B6*C6*D6*E6 -> 2.4943842 | I6: =H6*G6 -> 0.074831526 | J6: Census MRTS: health/personal care less pharmacies; original screening assumptions | K6: ACTIVE STUDY
A7: Electronics and appliances | B7: 91.183 | C7: 0.95 | D7: 0.7 | E7: 0.05 | F7: 14 | G7: =IF(F7>10,MIN(50%,INT(F7-10)*0.5%),0) -> 0.02 | H7: =B7*C7*D7*E7 -> 3.0318347 | I7: =H7*G7 -> 0.060636695 | J7: Census MRTS electronics/appliance stores; original screening assumptions | K7: ACTIVE STUDY
A8: Auto parts, accessories, and tires | B8: 134.398 | C8: 0.95 | D8: 0.55 | E8: 0.06 | F8: 14 | G8: =IF(F8>10,MIN(50%,INT(F8-10)*0.5%),0) -> 0.02 | H8: =B8*C8*D8*E8 -> 4.2133773 | I8: =H8*G8 -> 0.084267546 | J8: Census MRTS; original screening assumptions | K8: ACTIVE STUDY
A9: Hardware | B9: 41.862 | C9: 0.9 | D9: 0.25 | E9: 0.05 | F9: 13 | G9: =IF(F9>10,MIN(50%,INT(F9-10)*0.5%),0) -> 0.015 | H9: =B9*C9*D9*E9 -> 0.4709475 | I9: =H9*G9 -> 0.0070642125 | J9: Census MRTS hardware stores; original screening assumptions | K9: ACTIVE STUDY
A10: Furniture | B10: 71.782 | C10: 0.8 | D10: 0.9 | E10: 0.04 | F10: 13 | G10: =IF(F10>10,MIN(50%,INT(F10-10)*0.5%),0) -> 0.015 | H10: =B10*C10*D10*E10 -> 2.0673216 | I10: =H10*G10 -> 0.031009824 | J10: Census MRTS furniture stores; original screening assumptions | K10: ACTIVE STUDY
A11: Clothing | B11: 214.724 | C11: 0.9 | D11: 0.2 | E11: 0.15 | F11: 20 | G11: =IF(F11>10,MIN(50%,INT(F11-10)*0.5%),0) -> 0.05 | H11: =B11*C11*D11*E11 -> 5.797548 | I11: =H11*G11 -> 0.2898774 | J11: Census MRTS clothing stores; original screening assumptions | K11: ACTIVE STUDY
A12: Shoes | B12: 38.487 | C12: 0.95 | D12: 0.4 | E12: 0.2 | F12: 22 | G12: =IF(F12>10,MIN(50%,INT(F12-10)*0.5%),0) -> 0.06 | H12: =B12*C12*D12*E12 -> 2.925012 | I12: =H12*G12 -> 0.17550072 | J12: Census MRTS shoe stores; original screening assumptions | K12: ACTIVE STUDY
A13: Sporting goods | B13: 58.725 | C13: 0.9 | D13: 0.5 | E13: 0.07 | F13: 15 | G13: =IF(F13>10,MIN(50%,INT(F13-10)*0.5%),0) -> 0.025 | H13: =B13*C13*D13*E13 -> 1.8498375 | I13: =H13*G13 -> 0.046245938 | J13: Census MRTS sporting goods stores; original screening assumptions | K13: ACTIVE STUDY
A14: Office supplies and stationery | B14: 7.812 | C14: 0.9 | D14: 0.2 | E14: 0.15 | F14: 25 | G14: =IF(F14>10,MIN(50%,INT(F14-10)*0.5%),0) -> 0.075 | H14: =B14*C14*D14*E14 -> 0.210924 | I14: =H14*G14 -> 0.0158193 | J14: Census MRTS office supplies/stationery; original screening assumptions | K14: ACTIVE STUDY
A16: Total active screening study | B16: =SUM(B5:B14) -> 1191.962 | H16: =SUM(H5:H14) -> 86.106187 | I16: =SUM(I5:I14) -> 3.3070532 | J16: Official sales + model assumptions | K16: ACTIVE
A18: Interpretation: this is an original national market study rather than an observed SKU census. The active revenue estimate uses official annual sales, then applies explicit category-level screens for mass production, price above $100, prevalence of >10x fully loaded cost, and the PolicyBook calculator. Annual tax filings will replace assumptions with product-level price, unit cost, labor, and amortized R&D reports.

Sheet Loan_Scumming
A1: Loan Scumming Tax - 10-Year Audit and Large-Debt Payoff Tax
A2: The active model combines the 5% tax on annual debt payoffs above five times median salary with retroactive 10% taxation when the 10-year audit finds that asset-backed borrowing replaced realization of taxable income.
A4: Line | B4: Base / assumption | C4: Rate | D4: Revenue / result ($B) | E4: Treatment | F4: Source / status
A5: Securities-backed personal-use loans | B5: 138 | E5: Asset-backed borrowing stock | F5: Federal Reserve FEDS Note, 2024
A6: Margin loans | B6: 180 | E6: Asset-backed borrowing stock | F6: Federal Reserve / FINRA scale proxy
A7: Combined asset-backed borrowing stock | B7: =SUM(B5:B6) -> 318 | E7: Sum | F7: Active modeled stock
A8: Annual payoff turnover | B8: 0.25 | E8: Share of stock repaid annually | F8: Model assumption
A9: Annual large-debt payoff base | B9: =B7*B8 -> 79.5 | C9: 0.05 | D9: =B9*C9 -> 3.975 | E9: 5% transfer-tax base | F9: PolicyBook v86
A10: 10+ year audit-eligible share | B10: 0.25 | E10: Long-duration share | F10: Model assumption
A11: Audit finding rate for tax-avoidance use | B11: 0.5 | E11: Share recharacterized as income | F11: Model assumption
A12: Retroactively recharacterized income | B12: =B7*B10*B11 -> 39.75 | C12: 0.1 | D12: =B12*C12 -> 3.975 | E12: 10% income tax | F12: PolicyBook v86
A14: Total active Loan Scumming revenue | D14: =D9+D12 -> 7.95 | E14: Payoff tax plus retroactive income tax | F14: ACTIVE
A16: The implementation aggregates related loans and lenders by taxpayer so one payoff cannot be fragmented below the threshold. Primary-home acquisition mortgages and ordinary business operating loans remain outside the audit unless facts show they were used to avoid realization.

Sheet Protectorate_Fee
A1: Protectorate Fee - Legacy Active Country Base Restored
A2: The older tax study's active formula is restored: covered countries pay 1% of total national government expenditure for material reliance on United States defense protection while failing the adopted contribution standard.
A4: # | B4: Country | C4: Base year | D4: Government expenditure ($B) | E4: Fee rate | F4: Annual fee ($B)
A5: 1 | B5: Japan | C5: 2021 | D5: 2140.22 | E5: 0.01 | F5: =D5*E5 -> 21.4022
A6: 2 | B6: Germany | C6: 2022 | D6: 2025.63 | E6: 0.01 | F6: =D6*E6 -> 20.2563
A7: 3 | B7: United Kingdom | C7: 2022 | D7: 1386.19 | E7: 0.01 | F7: =D7*E7 -> 13.8619
A8: 4 | B8: Italy | C8: 2022 | D8: 1143.33 | E8: 0.01 | F8: =D8*E8 -> 11.4333
A9: 5 | B9: Canada | C9: 2022 | D9: 887.52 | E9: 0.01 | F9: =D9*E9 -> 8.8752
A10: 6 | B10: Mexico | C10: 2022 | D10: 427.43 | E10: 0.01 | F10: =D10*E10 -> 4.2743
A11: 7 | B11: South Korea | C11: 2021 | D11: 468.04 | E11: 0.01 | F11: =D11*E11 -> 4.6804
A12: 8 | B12: Australia | C12: 2021 | D12: 694.6 | E12: 0.01 | F12: =D12*E12 -> 6.946
A13: 9 | B13: Spain | C13: 2021 | D13: 722.98 | E13: 0.01 | F13: =D13*E13 -> 7.2298
A14: 10 | B14: Saudi Arabia | C14: 2021 | D14: 277.05 | E14: 0.01 | F14: =D14*E14 -> 2.7705
A15: 11 | B15: Netherlands | C15: 2021 | D15: 464.33 | E15: 0.01 | F15: =D15*E15 -> 4.6433
A16: 12 | B16: Turkey | C16: 2022 | D16: 253.93 | E16: 0.01 | F16: =D16*E16 -> 2.5393
... A81: 77 | B81: Mauritania | C81: 2021 | D81: 1.9 | E81: 0.01 | F81: =D81*E81 -> 0.019
A82: TOTAL | B82: 77 covered countries | D82: =SUM(D5:D81) -> 15140.38 | E82: =1% -> 0.01 | F82: =SUM(F5:F81) -> 151.4038
A84: Base years range from 2018 to 2022 and are carried forward from Michael Allen's Tax Study ModelSheet. The fee is active in the mature replacement model as directed; a future update may refresh each country's expenditure year without changing the statutory formula.

Sheet Citizen_Data_Royalty
A1: Citizen Data Royalty — 2024 U.S. Market Estimate
A2: 30% royalty on covered gross U.S. revenue attributable to collecting, compiling, profiling, licensing, targeting with, or otherwise monetizing citizen data. Collected through General Government and routed in full to the Citizen Wealth Fund.
A4: Sector / revenue channel | B4: Gross market ($B) | C4: U.S. share | D4: Citizen-data dependence | E4: Pre-overlap base ($B) | F4: Overlap deduction | G4: Overlap amount ($B) | H4: Net taxable base ($B) | I4: Royalty rate | J4: Royalty ($B) | K4: Source
A5: Digital advertising | B5: 258.6 | C5: 1 | D5: 0.57057231 | E5: =B5*C5*D5 -> 147.55 | F5: 0 | G5: =E5*F5 -> 0 | H5: =E5-G5 -> 147.55 | I5: 0.3 | J5: =H5*I5 -> 44.265 | K5: https://www.iab.com/insights/internet-advertising-revenue-report-full-year-2024/
A6: Data brokers and commercial data licensing | B6: 277.97 | C6: 0.3708 | D6: 1 | E6: =B6*C6*D6 -> 103.07128 | F6: 0.35 | G6: =E6*F6 -> 36.074947 | H6: =E6-G6 -> 66.996329 | I6: 0.3 | J6: =H6*I6 -> 20.098899 | K6: https://www.grandviewresearch.com/industry-analysis/data-broker-market-report
A7: Credit reporting, workforce and identity data | B7: 16.86 | C7: 0.73 | D7: 0.9 | E7: =B7*C7*D7 -> 11.07702 | F7: 0 | G7: =E7*F7 -> 0 | H7: =E7-G7 -> 11.07702 | I7: 0.3 | J7: =H7*I7 -> 3.323106 | K7: https://www.experianplc.com/content/dam/marketing/global/plc/en/assets/documents/reports/2024/experian_annual_report_2024_web.pdf
A8: Market research, panels and audience measurement | B8: 35.94 | C8: 1 | D8: 0.55 | E8: =B8*C8*D8 -> 19.767 | F8: 0.2 | G8: =E8*F8 -> 3.9534 | H8: =E8-G8 -> 15.8136 | I8: 0.3 | J8: =H8*I8 -> 4.74408 | K8: https://www.ibisworld.com/classifications/naics/541910/marketing-research-and-public-opinion-polling/
A9: Location intelligence | B9: 20.95 | C9: 0.2844 | D9: 0.55 | E9: =B9*C9*D9 -> 3.276999 | F9: 0.3 | G9: =E9*F9 -> 0.9830997 | H9: =E9-G9 -> 2.2938993 | I9: 0.3 | J9: =H9*I9 -> 0.68816979 | K9: https://www.grandviewresearch.com/industry-analysis/location-intelligence-market
A10: Vehicle telematics data services | B10: 7.1 | C10: 0.9 | D10: 0.25 | E10: =B10*C10*D10 -> 1.5975 | F10: 0.15 | G10: =E10*F10 -> 0.239625 | H10: =E10-G10 -> 1.357875 | I10: 0.3 | J10: =H10*I10 -> 0.4073625 | K10: https://www.maximizemarketresearch.com/market-report/north-america-telematics-market/88577/
A11: Lead generation and people-based prospect data | B11: 5.59 | C11: 0.405 | D11: 0.85 | E11: =B11*C11*D11 -> 1.9243575 | F11: 0.25 | G11: =E11*F11 -> 0.48108937 | H11: =E11-G11 -> 1.4432681 | I11: 0.3 | J11: =H11*I11 -> 0.43298044 | K11: https://www.rootsanalysis.com/lead-generation-market
A13: TOTAL | B13: =SUM(B5:B11) -> 623.01 | E13: =SUM(E5:E11) -> 288.26415 | G13: =SUM(G5:G11) -> 41.732161 | H13: =SUM(H5:H11) -> 246.53199 | J13: =SUM(J5:J11) -> 73.959598
A15: Policy control | B15: Treatment
A16: Name | B16: Citizen Data Royalty
A17: Collection | B17: Administered through General Government
A18: Routing | B18: 100% transferred to the Citizen Wealth Fund
A19: Treasury use | B19: Restricted; no ordinary General Government spending
A20: Double-count control | B20: Credit royalty already paid upstream on the same licensed dataset

Sheet Luxury_Tax
A1: Flat 5% Luxury Tax — 2024 Active Market Base
A2: Point-of-sale or import levy on qualifying nonproductive luxury purchases. The central base combines personal luxury goods, luxury and exotic vehicles, luxury yachts, and U.S. business jets. Productive business, industrial, agricultural, medical, educational, and ordinary household purchases are excluded.
A4: Market component | B4: 2024 U.S. base ($B) | C4: Taxable share | D4: Taxable base ($B) | E4: Flat rate | F4: Revenue ($B) | G4: Source / rationale
A5: Personal luxury goods | B5: 115.22 | C5: 1 | D5: =B5*C5 -> 115.22 | E5: 0.05 | F5: =D5*E5 -> 5.761 | G5: https://www.researchandmarkets.com/reports/6178771/united-states-luxury-goods-market-report-product
A6: Luxury and exotic vehicles | B6: 110 | C6: 1 | D6: =B6*C6 -> 110 | E6: 0.05 | F6: =D6*E6 -> 5.5 | G6: https://www.bcg.com/press/12december2025-us-luxury-exotic-car-market
A7: Luxury yachts | B7: 3.4 | C7: 1 | D7: =B7*C7 -> 3.4 | E7: 0.05 | F7: =D7*E7 -> 0.17 | G7: https://www.marketresearch.com/seek/Luxury-Goods-North-America/1831/1350/1.html
A8: U.S. business jets | B8: 12.6546 | C8: 1 | D8: =B8*C8 -> 12.6546 | E8: 0.05 | F8: =D8*E8 -> 0.63273 | G8: https://www.custommarketinsights.com/report/us-business-jet-market/
A10: TOTAL | B10: =SUM(B5:B8) -> 241.2746 | D10: =SUM(D5:D8) -> 241.2746 | F10: =SUM(F5:F8) -> 12.06373
A12: Statutory element | B12: Treatment
A13: Rate | B13: Flat 5%
A14: Collection point | B14: Retail sale, auction, registration, or import
A15: Business-use exclusion | B15: Allowed only for verified productive or operating use
A16: Primary-home treatment | B16: Outside this tax; land policy governed by LVT
A17: Used-goods treatment | B17: Tax only dealer/auction commercial sale; private household resale excluded
A18: Stacking | B18: May coexist with ordinary sales or excise taxes
A19: Anti-avoidance | B19: Related purchases and installment transfers aggregate to the full transaction price

Sheet PolicyBook_Update_Digest
A1: Policy Book Update Digest | Tax Overhaul v28 / Deep Tax Burden Study v35
A2: Emergency Revenue Bridge | B2: Emergency-only draw on dedicated-ledger surplus during a declared fiscal crisis; principal and corpus are never touched. | C2: Up to 15% of year surplus, 24-month cap, mandatory repayment | D2: 0 | E2: No fiscal impact (contingent mechanism only) | F2: PolicyBook Section 2. Governance safeguard; not modeled in the mature-year baseline.
A3: Policy area | B3: Approved change | C3: Rate / rule | D3: Active 2024 value ($B) | E3: Routing | F3: PolicyBook implementation text
A4: Liquid personal income | B4: Use cash or liquid income actually available to the individual; exclude Social Security, public assistance, and unavailable noncash accounting income. | C4: 10% individual tax; 3% citizen SS; HSA tiers | D4: 20470.758 | E4: General / SS / Healthcare | F4: One statutory liquid-income definition governs individual tax, citizen SS, and HSA calculations.
A5: Retirement income | B5: Include taxable pensions, annuities, traditional IRA and similar previously untaxed distributions. | C5: Included in liquid base | D5: 0 | E5: General / SS / Healthcare | F5: Tax the previously untaxed portion when distributed; do not tax return of after-tax principal.
A6: Royalties and cash receipts | B6: Include royalties, data-licensing payments, taxable legal settlements, and foreign cash income. | C6: Included in liquid base | D6: 0 | E6: General / SS / Healthcare | F6: All cash or liquid income available to the individual enters the common base unless expressly excluded.
A7: Estate and trust distributions | B7: Separate source-level levy on positive distributions. | C7: 3% | D7: 1.5033059 | E7: General Treasury | F7: Applies when assets or earnings are distributed to a beneficiary; coordinate credits to avoid duplicate tax.
A8: Anti-deferral real estate/entity tax | B8: Tax Form 4797 gains, positive REMIC residuals, deferred like-kind gains, and comparable trade-up/retention structures. | C8: 10% | D8: 28.270996 | E8: General Treasury | F8: A source-level anti-loophole levy; later individual distribution receives credit for tax already paid.
A9: Employer capital wages | B9: Employer SS applies to wages, bonuses, stock, RSUs, restricted stock, and equity awards. | C9: 3% | D9: 11.001 | E9: Social Security | F9: Value equity when the employee obtains an enforceable economic interest.
A10: Employer equity surtax | B10: Progressive employer-paid levy; active aggregate score retained. | C10: 9% aggregate model | D10: 33.003 | E10: General Treasury | F10: Marginal schedule through $1M; tranche above $1M set at adoption.
A11: Outsourcing Penalty | B11: Apply to qualifying firms outsourcing more than half of manufacturing. | C11: 10% | D11: 142.92019 | E11: General Treasury | F11: Active proxy uses related-party manufacturing imports pending firm-level customs testing.
A12: Fair Profit Tax | B12: Mass-produced physical products above $100 and priced more than 10x loaded materials, labor, and averaged R&D cost. | C12: PolicyBook calculator | D12: 3.3070532 | E12: General Treasury | F12: Exclude art, boutique/custom work, digital products, and SaaS.
A13: Loan Scumming | B13: 5% large-debt payoff tax plus 10% retroactive income treatment after avoidance audit. | C13: 5% + 10% | D13: 7.95 | E13: General Treasury | F13: Targets asset-backed personal borrowing used to avoid realization.
A14: Protectorate Fee | B14: Restore legacy 77-country calculation. | C14: 1% | D14: 151.4038 | E14: General Treasury | F14: Annual fee equals 1% of covered government expenditure for protected under-contributing states.
A15: Citizen Data Royalty | B15: Rename Citizen Data Tax; assess covered gross revenue from commercial citizen-data monetization. | C15: 30% | D15: 73.959598 | E15: Citizen Wealth Fund | F15: Collected through General Government and transferred in full to the Citizen Wealth Fund.
... A17: Federalized LVT | B17: Book the full federal land-rent capture scenario. | C17: Full scenario | D17: 2232.929 | E17: General Treasury | F17: Primary family residence exempt; no headline revenue haircut.
A18: Three-ledger standard | B18: General Government, Healthcare, and Social Security each publish their own balance, then consolidate once. | C18: No double counting | E18: All ledgers | F18: Internal transfers appear as expense in one ledger and funding in another, then eliminate in consolidation.
A19: Mature replacement baseline | B19: Model all approved mechanisms operating together under ordinary mature conditions. | C19: Active central case | E19: All ledgers | F19: Rollout costs and immature institutional stages remain separate from the recurring replacement-year headline.
A21: Emergency Revenue Bridge | B21: Emergency-only draw on dedicated-ledger surplus during a declared fiscal crisis; principal and corpus are never touched. | C21: Up to 15% of year surplus, 24-month cap, mandatory repayment | D21: 0 | E21: No fiscal impact (contingent mechanism only) | F21: PolicyBook Section 2. Governance safeguard; not modeled in the mature-year baseline.
A22: NHDC Charter Standard | B22: NHDC governed by a Charter Board split between a legislative health committee and executive cabinet appointees; both must approve before a change becomes a bill. | C22: Dual-body approval gate | D22: 0 | E22: No fiscal impact (governance only) | F22: PolicyBook Section 3. Does not alter the NHDC domestic price ceiling, export margin, or licensing revenue already booked.
A23: Citizenship Processing Clock | B23: Fixed 180-day processing clock on Contribution, Service, and Educational Citizenship applications; RCN rate drops to 3% for each day the government runs late. | C23: 180-day clock; late-day RCN penalty | D23: 0 | E23: No fiscal impact (administrative penalty, not modeled as revenue) | F23: PolicyBook Section 7. RCN base rate (7% employee / 7% employer) used in Noncitizen_SS_Model is unchanged; this is a compliance backstop, not a rate change.
A24: Permit Velocity Incentive | B24: States clearing 90% of Class Permit System filings on time for three years earn federal siting and grant priority; states falling below 90% for two years lose it. | C24: Priority-tier eligibility test | D24: 0 | E24: No fiscal impact (allocation priority, not a new outlay or revenue line) | F24: PolicyBook Section 16. Does not change any booked infrastructure, campus, or freeport revenue line.
A25: NMA Custodianship of the National Lending Authority | B25: NLA becomes a chartered subsidiary of the NMA, governed by the same Charter Board structure as NHDC. | C25: Dual-body approval gate | D25: 0 | E25: No fiscal impact (governance only) | F25: PolicyBook Section 18. NLA fixed 10% lending rate and NLA_Model profit ramp are unchanged.
A26: Lending Authority Ledger Lock | B26: NLA fixed rate and NMA mandate protected by Charter Board approval plus a two-thirds House and Chamber of Communities vote. | C26: Supermajority amendment protection | D26: 0 | E26: No fiscal impact (governance only) | F26: PolicyBook Section 18. Protects, but does not alter, the NLA_Model and NLA domestic/institutional profit figures already booked.

Sheet Idle_Wealth_Levy
A1: 1% Idle Wealth Levy - Concentrated Nonproductive Financial Reserves
A2: Excise on the privilege of maintaining ultra-large, nonproductive financial reserves. The levy is measured by covered net asset value, with full credits for productive deployment and for tax paid at another ownership tier.
A4: Tax-base component | B4: Gross pool ($B) | C4: Exclusion / covered share | D4: Net covered base ($B) | E4: Rate | F4: Revenue ($B) | G4: Source / treatment
A5: Individuals: top 0.1% corporate equities and mutual-fund shares | B5: 11556.136 | C5: 0.85 | D5: =B5*C5*C6 -> 3437.9505 | E5: 0.01 | F5: =D5*E5 -> 34.379505 | G5: Federal Reserve DFA, 2024 Q4. Removes 15% for threshold allowance, retirement/public-interest accounts, and reporting mismatch.
A6: Individual nonproductive share after exclusions | C6: 0.35 | D6: =D5 -> 3437.9505 | E6: 0.01 | F6: =0 -> 0 | G6: Central case: 35% lacks a qualifying productive-deployment safe harbor.
A7: Managed idle assets: hedge-fund net asset value | B7: 5334 | C7: 0.25 | D7: =B7*C7 -> 1333.5 | E7: 0.01 | F7: =D7*E7 -> 13.335 | G7: SEC Form PF, 2024 Q4. Managers assess and remit the levy on behalf of beneficial clients from covered managed assets.
A8: Cross-tier credit | C8: 0 | D8: =0 -> 0 | E8: 0.01 | F8: =0 -> 0 | G8: No credit. A managed-asset levy and an individual-level levy may both apply when each statutory base is independently satisfied.
A10: Central booked result
A11: Individual covered base | D11: =D5 -> 3437.9505 | G11: After threshold and productive-deployment exclusions
A12: Managed idle-asset base | D12: =D7 -> 1333.5 | G12: Manager remits on behalf of clients; levy may coexist with an individual-level assessment
A13: Total certified Idle Wealth base | D13: =SUM(D11:D12) -> 4771.4505 | E13: 0.01 | F13: =D13*E13 -> 47.714505 | G13: Art, collectibles, offshore wrappers, and other stores of value remain legally covered but booked at zero until reporting exists
A15: Scenario analysis
A16: Scenario | B16: Individual idle share | C16: Managed-asset idle share | D16: Cross-tier credit | E16: Tax base ($B) | F16: Revenue ($B) | G16: Budget implication
A17: Low | B17: 0.2 | C17: 0.15 | D17: 0 | E17: =$B$5*$C$5*B17+$B$7*C17 -> 2764.6431 | F17: =E17*$E$13 -> 27.646431 | G17: Balances the pre-change budget with a small recurring margin
A18: Central | B18: 0.35 | C18: 0.25 | D18: 0 | E18: =$B$5*$C$5*B18+$B$7*C18 -> 4771.4505 | F18: =E18*$E$13 -> 47.714505 | G18: Produces a stronger recurring consolidated surplus
A19: High | B19: 0.5 | C19: 0.35 | D19: 0 | E19: =$B$5*$C$5*B19+$B$7*C19 -> 6778.2578 | F19: =E19*$E$13 -> 67.782578 | G19: Creates a larger debt-reduction margin
A21: Statutory base rules
A22: Covered taxpayer | G22: Individuals and pooled speculative funds. Trusts and estates remain under separate taxes unless acting as wrappers for a covered taxpayer.
A23: Threshold | G23: Individual coverage begins only above 100 times median U.S. retirement wealth, presently modeled near $150 million.
A24: Covered assets | G24: Concentrated public securities, fund interests, art, collectibles, offshore financial wrappers, and equivalent stores of financial value.
A25: Productive safe harbor | G25: New issues, direct business capitalization, domestic plant and equipment, qualified venture investment, infrastructure, active lending, and genuine operating-control stakes.
A26: Managed-asset levy | G26: The beneficial client owes the tax. The manager calculates, withholds, and remits it from the covered account as statutory paying agent.
A27: No cross-tier credit | G27: The managed-asset levy and individual levy are separate charges. Both may apply when the fund-level and individual-level statutory bases are independently met.
A28: Buy-Borrow-Die | G28: Personal borrowing secured by covered idle assets remains in the covered base and cannot reduce net value.
A29: Payment | G29: Annual withholding by managers or direct payment by individuals. A four-year Tax Debt schedule remains available for genuinely illiquid assets.

Sheet Total_Government_Revenue
A1: Total Government Revenue View - Year 10 Mature Fully Inclusive Model
A2: All Policy Book taxes, duties, royalties, contributions, public-enterprise earnings, spectrum receipts, enterprise services, and mature public-investment earnings are included once. LVT is carried unchanged.
A4: Revenue class | B4: Amount ($B) | C4: Included in Total Government Revenue | D4: Included in operating Treasury | E4: Treatment
A5: Unrestricted General Treasury revenue | B5: =Tax_Revenue_2024!D33 -> 5710.9312 | C5: Yes | D5: Yes | E5: Tax_Revenue_2024 unrestricted subtotal
A6: Citizen Data Royalty | B6: 73.959598 | C6: Yes | D6: No | E6: Dedicated to Citizen Wealth Fund
A7: Citizen Social Security contribution | B7: 614.12274 | C7: Yes | D7: No | E7: Dedicated Social Security revenue
A8: Employer Social Security contribution | B8: 362.26773 | C8: Yes | D8: No | E8: Dedicated Social Security revenue
A9: Resident Contributor incremental contribution | B9: 52.407964 | C9: Yes | D9: No | E9: Dedicated Social Security revenue
A10: NLA domestic distributable profit | B10: =NLA_Model!E23 -> 154.13732 | C10: Yes | D10: No | E10: Dedicated Social Security earnings at Year 10 NLA maturity
A11: NLA institutional/international earnings | B11: 12 | C11: Yes | D11: No | E11: Dedicated Social Security earnings
A12: Social Security trust investment income | B12: 193.05 | C12: Yes | D12: No | E12: Public investment earnings
A13: National Continuity Contribution | B13: =National_Continuity!D22 -> 559.2898 | C13: Yes | D13: No | E13: Year 10 gross NCC; SS to breakeven, residual to NIRF
A14: State/local governmental healthcare funding | B14: 658 | C14: Yes | D14: No | E14: Government revenue retained in national healthcare floor
A15: NHDC international export margin | B15: 82.5825 | C15: Yes | D15: No | E15: Foreign commercial earnings
A16: NHDC international license earnings | B16: 12 | C16: Yes | D16: No | E16: Foreign licensing and manufacturing-contract earnings
A17: Sin sales surtax | B17: 26.5 | C17: Yes | D17: No | E17: Dedicated catastrophic-care revenue
A18: Employer catastrophic-care contribution | B18: 585.44455 | C18: Yes | D18: No | E18: Restricted national healthcare pool
A19: Spectrum NIRF capital receipt | B19: 6 | C19: Yes | D19: No | E19: Protected NIRF principal
A20: Citizen-owned HSA contributions | B20: 742.34133 | C20: No | D20: No | E20: Private citizen assets
A21: Employer HSA match | B21: 585.44455 | C21: No | D21: No | E21: Worker-owned account funding
A23: Summary
A24: Total Government Revenue | B24: =SUM(B5:B19) -> 9102.6934 | E24: All external government collections and public earnings
A25: Operating General Treasury Revenue | B25: =B5 -> 5710.9312 | E25: Available for ordinary General Government operations
A26: Dedicated Government Revenue | B26: =B24-B25 -> 3391.7622 | E26: Legally unavailable for ordinary operations
A27: Private Mandated System Funding | B27: =SUM(B20:B21) -> 1327.7859 | E27: Citizen HSA plus employer HSA match
A28: Consolidated Replacement Balance | B28: =Deficit_Views!B46 -> 1079.531 | E28: System-wide balance after operating costs and transfers

Sheet Offshore_Capital_Duty
A1: Offshore Capital Export Duty - Central Budget Estimate
A2: 10% duty on covered outbound capital above the rolling $1 million threshold. Bona fide U.S.-company foreign expansion is excluded and remains subject to the separate outsourcing rules where applicable.
A4: Base component | B4: 2024 amount ($B) | C4: Covered share | D4: Behavioral share remaining | E4: Duty rate | F4: Booked revenue ($B)
A5: U.S. portfolio investment abroad | B5: 361 | C5: 0.9 | D5: 0.45 | E5: 0.1 | F5: =B5*C5*D5*E5 -> 14.6205
A6: U.S. deposits, loans, and other foreign investment | B6: 113.6 | C6: 0.9 | D6: 0.45 | E6: 0.1 | F6: =B6*C6*D6*E6 -> 4.6008
A7: Bona fide U.S.-company foreign expansion / direct investment | B7: 379.1 | C7: 0 | D7: 0 | E7: 0.1 | F7: 0
A8: Official reserve assets | B8: 2.1 | C8: 0 | D8: 0 | E8: 0.1 | F8: 0
A10: Central modeled calculation | B10: =SUM(B5:B6) -> 474.6 | C10: =AVERAGE(C5:C6) -> 0.9 | D10: =AVERAGE(D5:D6) -> 0.45 | E10: 0.1 | F10: =SUM(F5:F6) -> 19.2213
A12: Budget-booked revenue | F12: 19.2
A14: Carveout | F14: Registered foreign operating expansion, acquisition, manufacturing, distribution, research, logistics, and working capital
A15: Not carved out | F15: Passive securities, offshore cash parking, personal foreign real estate, art, bullion, trusts, and disguised value transfers
A16: Commercial-payment exclusion | F16: Fair-market payments for completed goods and services remain excluded
A17: Collection | F17: Withheld by banks, custodians, broker-dealers, processors, registries, and other controlled intermediaries
A18: Source | F18: https://www.bea.gov/news/2025/us-international-transactions-4th-quarter-and-year-2024

Sheet High_Wealth_Compliance
A1: High-Wealth Withholding and Compliance Recovery
A2: Collection and recovery mechanism only. It creates no new statutory tax rate and moves payment to controlled intermediaries.
A4: Scenario | B4: Addressable unpaid liability ($B) | C4: Recovery rate | D4: Gross recovery ($B) | E4: Current-enforcement overlap | F4: Net recovery ($B)
A5: Low | B5: 100 | C5: 0.2 | D5: =B5*C5 -> 20 | E5: 0.1 | F5: =D5*(1-E5) -> 18
A6: Central | B6: 140 | C6: 0.3 | D6: =B6*C6 -> 42 | E6: 0.095238095 | F6: =D6*(1-E6) -> 38
A7: High | B7: 180 | C7: 0.4 | D7: =B7*C7 -> 72 | E7: 0.1 | F7: =D7*(1-E7) -> 64.8
A9: Budget-booked net recovery | F9: 38
A11: Automatic withholding/reporting channel | F11: Partnership and private-fund distributions
F12: Trust distributions and loans
F13: Offshore account transfers
F14: Large securities-backed loans
F15: Private-equity management allocations
F16: Custodied digital-asset transfers
F17: Art and collectible auction settlements
F18: Foreign-entity payments to American beneficial owners
F19: Closely held company redemptions and large related-party asset sales
A20: Sources | F20: https://www.irs.gov/statistics/irs-the-tax-gap ; https://www.gao.gov/products/gao-23-106020

Sheet Cost_Savings_Program
A1: FEDERAL COST SAVINGS PROGRAM | MATURE-YEAR CENTRAL CASE
A2: Average recurring annual savings after implementation reaches ordinary capacity. Estimates use realistic central or midpoint assumptions, with overlap removed before budget booking.
A4: A. FEDERAL INTEGRITY AND EXECUTION REFORM
A5: Savings channel | B5: Annual savings ($B) | C5: Treatment | D5: Basis | E5: Validation note | F5: Primary source
A6: Improper-payment prevention and correction | B6: 72.5 | C6: Booked | D6: Midpoint of $60B-$85B modeled range | E6: FY2025 reported improper payments were about $186B; estimate does not treat all improper payments as recoverable fraud | F6: https://www.gao.gov/products/gao-26-108694
A7: Procurement fraud, defective pricing, and overbilling | B7: 11.5 | C7: Booked | D7: Midpoint of $8B-$15B modeled range | E7: Targets fraud, defective pricing, overbilling, and false claims rather than ordinary sourcing savings | F7: https://www.gao.gov/highrisk/dod-weapon-systems-acquisition
A8: Acquisition and federal IT execution reform | B8: 16 | C8: Booked | D8: Midpoint of $10B-$22B modeled range | E8: Modular delivery, stop-loss gates, milestone payment, and termination rights | F8: https://www.gao.gov/products/gao-25-107604
A9: Duplication, overlap, and administrative consolidation | B9: 15 | C9: Booked | D9: Midpoint of $10B-$20B modeled range | E9: Government-wide consolidation and shared services | F9: https://www.gao.gov/products/gao-26-108505
A10: Infrastructure estimating and delivery controls | B10: 7 | C10: Booked | D10: Midpoint of $4B-$10B modeled range | E10: Reference-class estimates, scope lock, independent review, and holdbacks | F10: https://www.gao.gov/highrisk
A11: Aid diversion, grant fraud, and partner controls | B11: 2 | C11: Booked | D11: Midpoint of $1B-$3B modeled range | E11: Traceability, tranche payments, implementer liability, and adversary controls | F11: https://oig.usaid.gov/
A12: Recoveries and asset forfeiture | B12: 5 | C12: Booked | D12: Midpoint of $3B-$7B modeled range | E12: Restitution, disgorgement, beneficial-owner tracing, and successor liability | F12: https://www.justice.gov/civil/false-claims-act
A13: Integrity systems, enforcement, and appeals cost | B13: -14 | C13: Booked cost | D13: Conservative annual operating allowance | E13: Verification infrastructure, inspectors, investigators, cybersecurity, and appeals | F13: https://www.gao.gov/products/gao-26-108044
A14: NET BASE INTEGRITY SAVINGS | B14: =SUM(B6:B13) -> 115 | C14: BOOKED | D14: Existing central package
A16: B. PROCUREMENT, GRANTS, WORKFORCE, CREDIT, AND MILITARY REPAIR
A17: Policy channel | B17: Gross annual savings ($B) | C17: Treatment | D17: Called-out basis | E17: Validation note | F17: Primary source
A18: Unified procurement aggregation and reference pricing | B18: 45 | C18: Gross policy value | D18: $300B addressable common procurement × 15% midpoint savings | E18: GAO cites leading commercial strategic-sourcing savings of 10%-20%; 15% is the midpoint | F18: https://www.gao.gov/assets/gao-21-40.pdf
A19: Grant delivery and pass-through control | B19: 5 | C19: Gross policy value | D19: $500B addressable multilayer grant flow × 1% | E19: The 1% factor is a model assumption because no single government-wide GAO rate exists | F19: https://www.gao.gov/duplication-cost-savings
A20: Federal workforce and contractor structure reform | B20: 8 | C20: Gross policy value
A21: Subsidy and federal credit performance | B21: 3 | C21: Gross policy value | D21: Program-specific repricing, consolidation, termination, and recovery | E21: Conservative share of identified credit subsidy and fair-value exposure | F21: https://www.cbo.gov/budget-options
A22: Military right to repair, reproduce, and compete sustainment | B22: 9 | C22: Gross policy value | D22: $150B addressable sustainment and repair activity × 6% | E22: GAO reports operating and support costs are about 70% of lifecycle cost; savings estimate applies only to an addressable subset | F22: https://www.gao.gov/products/gao-24-107378
A23: Implementation and technical-data acquisition cost | B23: -4 | C23: Booked cost | D23: Government data rights, catalog systems, contract conversion, and review | E23: Offsets near-term and recurring administration required to sustain the package | F23: https://www.gao.gov/products/gao-24-107378
A24: GROSS NEW POLICY PACKAGE, NET OF DIRECT COST | B24: =SUM(B18:B23) -> 66 | C24: Policy value | D24: Sum of rows 18-23
A25: Less overlap with existing procurement and duplication savings | B25: -17 | C25: Overlap removal | D25: Removes value already represented in the $11.5B procurement and $15B duplication lines | E25: Prevents double counting while preserving the stronger policy basis
A26: NET ADDITIONAL NONOVERLAPPING SAVINGS | B26: =B24+B25 -> 49 | C26: BOOKED | D26: New savings beyond the existing $115B package
A27: TOTAL MATURE-YEAR COST SAVINGS | B27: =B14+B26 -> 164 | C27: ACTIVE HEADLINE | D27: Base integrity package plus nonoverlapping additions | E27: Full amount booked because the model represents an average mature year
A29: C. BUDGET EFFECT
A30: Budget measure | B30: Amount ($B)
A31: Pre-savings consolidated replacement surplus | B31: 75.523448
A32: Total mature-year cost savings | B32: =B27 -> 164
A33: Revised consolidated replacement surplus | B33: =B31+B32 -> 239.52345
A34: Revised ordinary General Government outlays | B34: =2024_Basis_Control!B9-2024_Basis_Control!B11-2024_Basis_Control!B13-B27 -> 3460
A35: Strict Treasury balance after Social Security support | B35: =Deficit_Views!B49 -> 318.95606
A37: D. CONTINUING COST-REDUCTION RESEARCH
A38: Priority | B38: Target area | C38: Initial mechanism | D38: Booking posture | E38: Evidence needed | F38: Primary source
A39: 1 | B39: Debt-service and cash management | C39: Improve cash forecasting, shorten idle cash cycles, and retire high-cost debt where advantageous | D39: Do not book until Treasury model is built | E39: Maturity structure, liquidity constraints, and refinancing effects | F39: https://www.cbo.gov/publication/60843/html
A40: 2 | B40: Federal real property | C40: Dispose of unneeded buildings, consolidate leases, and stop maintaining obsolete stock | D40: Research target | E40: Property utilization, disposal proceeds, lease exit costs, and mission need | F40: https://www.gao.gov/products/gao-25-108028
A41: 3 | B41: Government-wide IT portfolio | C41: Eliminate duplicate systems and terminate nonperforming modernization programs | D41: Research target | E41: Portfolio inventory, lifecycle cost, overlap, and termination cost | F41: https://www.gao.gov/products/gao-25-107604

Sheet SS_Year_0_4_10
A1: SOCIAL SECURITY FLOOR, RESIDENT CONTRIBUTOR SYSTEM, AND NATIONAL CONTINUITY CONTRIBUTION | YEAR 0, YEAR 4, YEAR 10
A2: Family and broader labor-growth effects remain excluded. Social Security is funded through citizen and employer contributions, Resident Contributor receipts, NLA profit, trust income, noncitizen benefit exclusions, and the National Continuity Contribution. NHDC is fully independent.
A4: MODEL ASSUMPTIONS
A5: Assumption | B5: Value | C5: Unit / treatment | D5: Source / basis
A6: Protected Social Security trust floor | B6: 2700 | C6: $B | D6: Adopted policy floor
A7: Central blended trust return | B7: 0.0715 | C7: Nominal model yield | D7: 50% CWF index / 50% diversified sleeve
A8: Real growth in citizen and employer contribution bases | B8: 0.012 | C8: Annual real growth | D8: Central projection assumption
A9: OASDI cost-rate ratio, Year 4 vs Year 0 | B9: 1.0240729 | C9: Ratio | D9: 2026 Trustees intermediate cost-rate path
A10: OASDI cost-rate ratio, Year 10 vs Year 0 | B10: 1.0318803 | C10: Ratio | D10: 2026 Trustees intermediate cost-rate path
A11: General Government balance before SS support | B11: 34.934671 | C11: $B, real | D11: Deep Study v28
A12: Healthcare annual balance before waterfall | B12: 364.50949 | C12: $B, real | D12: Deep Study v28 | E12: Additional studied controls | F12: Year 0 | G12: Treatment
A13: Protected healthcare reserve floor | B13: 120 | C13: $B | D13: Adopted policy floor | E13: Social Security payment accuracy saving | F13: 6 | G13: Incremental recoverable improper-payment reduction
A14: Healthcare surplus available above reserve
A16: A. ADOPTED FUNDING WATERFALL
A17: Measure | B17: Year 0 | C17: Year 4 | D17: Year 10 | E17: Treatment | F17: Formula basis | G17: Status
A18: Protected SS trust corpus | B18: 2700 | C18: 2700 | D18: 2700 | E18: Treasury prevents any fall below floor | F18: Constant statutory floor | G18: Adopted
A19: Citizen + employer contributions + NLA profit | B19: =SS_Hybrid_2024!D9+NLA_Model!E21 -> 997.86225 | C19: =SS_Hybrid_2024!D9*(1+$B$8)^4+NLA_Model!E22 -> 1091.8206 | D19: =SS_Hybrid_2024!D9*(1+$B$8)^10+NLA_Model!E23 -> 1254.2284 | E19: Dedicated non-trust funding | F19: Contribution bases grow 1.2%; NLA follows startup, full-term, and maturity cases | G19: Calculated
A20: Trust investment income | B20: =$B$6*$B$7 -> 193.05 | C20: =$B$6*$B$7 -> 193.05 | D20: =$B$6*$B$7 -> 193.05 | E20: Dedicated investment income | F20: $2.7T × 7.15% | G20: Calculated
A21: Total SS funding before transfers | B21: =B19+B20 -> 1190.9122 | C21: =C19+C20 -> 1284.8706 | D21: =D19+D20 -> 1447.2784 | E21: Dedicated funding | F21: Non-trust + trust income | G21: Calculated
A22: Net OASDI obligation after payment-accuracy saving | B22: =1485-6 -> 1479 | C22: =1485*(1+$B$8)^4*$B$9-6 -> 1589.0686 | D22: =1485*(1+$B$8)^10*$B$10-6 -> 1720.4774 | E22: Gross scheduled cost less $6B dedicated payment-accuracy saving | F22: Year 0: $1.485T gross less $6B = $1.479T; later years grow the gross cost path, then deduct $6B | G22: Calculated
A23: SS gap before NCC | B23: =MAX(0,B22-B21-Noncitizen_SS_Model!B30-Noncitizen_SS_Model!B31-12) -> 205.67979 | C23: =MAX(0,C22-C21-Noncitizen_SS_Model!C30-Noncitizen_SS_Model!C31-12) -> 217.89468 | D23: =MAX(0,D22-D21-Noncitizen_SS_Model!D30-Noncitizen_SS_Model!D31-12) -> 181.22434 | E23: First claim on National Continuity Contribution | F23: Spending less dedicated funding, RCN effects, benefit savings, and NLA international earnings | G23: Calculated
A24: Healthcare balance before independent waterfall | B24: 364.50949 | C24: 364.50949 | D24: 364.50949 | E24: Annual healthcare surplus | F24: Held constant in real terms | G24: Calculated
A25: Healthcare reserve retained | B25: =$B$13 -> 120 | C25: =$B$13 -> 120 | D25: =$B$13 -> 120
A26: Healthcare excess available | B26: =B24-B25 -> 244.50949 | C26: =C24-C25 -> 244.50949 | D26: =D24-D25 -> 244.50949 | E26: Transferable only after reserve floor | F26: Balance less reserve | G26: Calculated
A27: NCC transfer to Social Security | B27: =National_Continuity!B24 -> 205.67979 | C27: =National_Continuity!C24 -> 217.89468 | D27: =National_Continuity!D24 -> 181.22434 | E27: First priority from NCC | F27: Lesser of SS gap and gross NCC revenue | G27: Calculated
A28: Residual Treasury support to Social Security | B28: =National_Continuity!B27 -> 0 | C28: =National_Continuity!C27 -> 0 | D28: =National_Continuity!D27 -> 0 | E28: Backstop needed to protect $2.7T trust floor | F28: Remaining SS gap after healthcare transfer | G28: Calculated
A29: Social Security ending balance | B29: =B21+12+Noncitizen_SS_Model!B30+Noncitizen_SS_Model!B31+National_Continuity!B24+National_Continuity!B27-B22 -> 0 | C29: =C21+12+Noncitizen_SS_Model!C30+Noncitizen_SS_Model!C31+National_Continuity!C24+National_Continuity!C27-C22 -> 0 | D29: =D21+12+Noncitizen_SS_Model!D30+Noncitizen_SS_Model!D31+National_Continuity!D24+National_Continuity!D27-D22 -> 0 | E29: Balanced after transfers | F29: Funding plus transfers less spending | G29: Calculated
A30: NIRF residual from NCC | B30: =National_Continuity!B26 -> 290.72021 | C30: =National_Continuity!C26 -> 302.76485 | D30: =National_Continuity!D26 -> 378.06546 | E30: Available after SS is balanced | F30: Healthcare excess less SS transfer | G30: Calculated
A31: Healthcare residual to NIRF | B31: =National_Continuity!B32 -> 122.25475 | C31: =National_Continuity!C32 -> 122.25475 | D31: =National_Continuity!D32 -> 122.25475 | E31: 50% of residual | F31: Equal split | G31: Calculated
A32: Healthcare residual to Citizen Wealth Fund | B32: =National_Continuity!B33 -> 122.25475 | C32: =National_Continuity!C33 -> 122.25475 | D32: =National_Continuity!D33 -> 122.25475 | E32: 50% of residual | F32: Equal split | G32: Calculated
A33: Strict Treasury balance after SS floor support | B33: =National_Continuity!B34 -> 37.156061 | C33: =National_Continuity!C34 -> 37.156061 | D33: =National_Continuity!D34 -> 37.156061 | E33: General balance less Treasury backstop | F33: Internal healthcare transfer excluded | G33: Calculated
A34: Consolidated federal balance | B34: =Budget_0_4_10!B23 -> 992.18577 | C34: =Budget_0_4_10!C23 -> 1004.2304 | D34: =Budget_0_4_10!D23 -> 1079.531 | E34: All public reserves and fund allocations counted once | F34: Fully inclusive budget path with gross NCC counted once | G34: Calculated
A36: B. WATERFALL PRIORITY
A37: Priority | B37: Destination | C37: Rule | D37: Normal-year treatment | E37: Emergency treatment | F37: Fiscal effect | G37: Status
A38: 1 | B38: Healthcare reserve | C38: Retain $120B before any transfer | D38: Protected reserve | E38: Pandemic/disaster costs may retain or use all healthcare surplus | F38: Public reserve | G38: Adopted
A39: 2 | B39: Social Security | C39: Use healthcare surplus above reserve to close annual SS gap | D39: First transfer priority | E39: Emergency healthcare needs temporarily supersede transfer | F39: Internal transfer | G39: Adopted
A40: 3 | B40: NHDC and public-health R&D / capacity | C40: Fund through approved healthcare operating budgets and retained operating margins | D40: Programmatic appropriation before distributable profit | E40: Pandemic/disaster response receives priority | F40: Healthcare expenditure, separately costed | G40: Policy rule
A41: 4 | B41: NIRF and CWF | C41: Split distributable residual 50/50 | D41: Only after SS balance and approved healthcare needs | E41: May be suspended for emergency response | F41: Public capital allocation | G41: Adopted
A42: 5 | B42: General discretionary use | C42: Available only when SS and both national funds meet statutory health tests | D42: Last priority | E42: Emergency appropriations may override | F42: Treasury discretion | G42: Policy rule
A44: FINDINGS
A45: Finding | B45: Result
A46: Year 0 | B46: Healthcare excess closes the entire Social Security gap. Treasury support is not required. $84.589B remains for a 50/50 NIRF/CWF split.
A47: Year 4 | B47: Healthcare excess closes the entire Social Security gap. Treasury support is not required. $31.272B remains for a 50/50 NIRF/CWF split.
A48: Year 10 | B48: Healthcare excess covers most of the Social Security gap. Treasury supplies the remaining $12.158B to preserve the $2.7T trust floor.

Sheet Noncitizen_SS_Model
A1: CITIZEN-ONLY SOCIAL SECURITY | NONCITIZEN FISCAL MODEL
A2: Baseline citizen and labor-force growth remains unchanged. This module isolates the new 7% employee / 7% employer noncitizen contribution and the elimination of noncitizen Social Security benefits.
A4: A. CONTRIBUTION BASE
A5: Input | B5: Central value | C5: Unit / formula | D5: Treatment | E5: Validation | F5: Source
A6: Employed noncitizens | B6: 14.865652 | C6: Millions | D6: 2024 employed noncitizen population | E6: ACS-derived count | F6: https://www.migrationpolicy.org/data/state-profiles/state/workforce/US
A7: Modeled average annual liquid earnings | B7: 46000 | C7: $ per worker | D7: Central average after allowing for part-time work; BLS full-time foreign-born median was $52,052 | E7: Model assumption, explicitly below full-time median | F7: https://www.bls.gov/news.release/forbrn.t05.htm
A8: Wage-and-liquid-income base | B8: =B6*B7/1000 -> 683.81999 | C8: $B | D8: Workers × modeled average earnings | E8: Employee-side contribution base
A9: Employer-covered share | B9: 0.916 | C9: Share | D9: Private wage/salary plus government-worker share | E9: Excludes self-employed and unpaid family workers from employer match | F9: https://www.migrationpolicy.org/data/state-profiles/state/workforce/US
A10: Employer compensation base | B10: =B8*B9 -> 626.37911 | C10: $B | D10: Income base × employer-covered share | E10: Employer-side contribution base
A11: Citizen baseline employee rate | B11: 0.03 | C11: Rate | D11: Existing Deep Study treatment
A12: Citizen baseline employer rate | B12: 0.03 | C12: Rate | D12: Existing Deep Study treatment
A13: Noncitizen employee rate | B13: 0.07 | C13: Rate | D13: Policy Book v86.8
A14: Noncitizen employer rate | B14: 0.07 | C14: Rate | D14: Policy Book v86.8
A15: Baseline 3% + 3% contribution | B15: =B8*B11+B10*B12 -> 39.305973 | C15: $B | D15: Existing amount already inside the model
A16: New 7% + 7% contribution | B16: =B8*B13+B10*B14 -> 91.713937 | C16: $B | D16: Total contribution under adopted policy
A17: Incremental contribution revenue | B17: =B16-B15 -> 52.407964 | C17: $B | D17: New contribution less baseline contribution | E17: Added to OASDI trust funding
A19: B. BENEFIT SAVINGS
A20: Benefit category | B20: Annual savings ($B) | C20: Treatment | D20: Called-out basis | E20: Confidence | F20: Source
A21: OASDI benefits to noncitizens | B21: 18 | C21: Central modeled saving | D21: Modeled 1.2M affected beneficiaries at $1,250 average monthly benefit | E21: Medium-low: SSA does not publish a complete current citizenship cross-tab for all OASDI beneficiaries | F21: https://www.ssa.gov/faqs/en/questions/KA-02447.html
A22: Federal SSI paid to noncitizens | B22: =319391*579.59*12/1000000000 -> 2.22139 | C22: Verified current-flow saving | D22: 319,391 recipients × $579.59 average monthly payment × 12 | E22: High for December-flow annualization | F22: https://www.ssa.gov/policy/docs/statcomps/ssi_asr/2024/sect02.html
A23: Noncitizen SSI recipients receiving Social Security income | B23: 190650 | C23: Recipients | D23: Subset confirming material overlap between SSI and OASDI | E23: Administrative count | F23: https://www.ssa.gov/policy/docs/statcomps/ssi_asr/2024/sect05.html
A24: State Social Security supplements | B24: 0 | C24: $B booked | D24: Not booked without a complete state-by-state expenditure base | E24: Potential additional state saving
A25: OASDI ledger improvement | B25: =B17+B21 -> 70.407964 | C25: $B | D25: Incremental contributions + OASDI benefit savings | E25: Used in Social Security ledger
A26: Government-wide improvement including SSI | B26: =B25+B22 -> 72.629354 | C26: $B | D26: OASDI improvement + federal SSI saving | E26: SSI remains a General Government saving
A28: C. YEAR 0 / YEAR 4 / YEAR 10 EFFECT
A29: Measure | B29: Year 0 | C29: Year 4 | D29: Year 10 | E29: Projection treatment | F29: Status
A30: Incremental noncitizen contributions | B30: =$B$17*(1+SS_Year_0_4_10!$B$8)^0 -> 52.407964 | C30: =$B$17*(1+SS_Year_0_4_10!$B$8)^4 -> 54.96919 | D30: =$B$17*(1+SS_Year_0_4_10!$B$8)^10 -> 59.047622 | F30: Calculated
A31: OASDI benefit savings | B31: =$B$21*(1+SS_Year_0_4_10!$B$8)^0*IF(0<=4,1+(SS_Year_0_4_10!$B$9-1)*0/4,SS_Year_0_4_10!$B$9*(1+(SS_Year_0_4_10!$B$10/SS_Year_0_4_10!$B$9-1)*(0-4)/6)) -> 18 | C31: =$B$21*(1+SS_Year_0_4_10!$B$8)^4*IF(4<=4,1+(SS_Year_0_4_10!$B$9-1)*4/4,SS_Year_0_4_10!$B$9*(1+(SS_Year_0_4_10!$B$10/SS_Year_0_4_10!$B$9-1)*(4-4)/6)) -> 19.334165 | D31: =$B$21*(1+SS_Year_0_4_10!$B$8)^10*IF(10<=4,1+(SS_Year_0_4_10!$B$9-1)*10/4,SS_Year_0_4_10!$B$9*(1+(SS_Year_0_4_10!$B$10/SS_Year_0_4_10!$B$9-1)*(10-4)/6)) -> 20.926999 | F31: Calculated
A32: Federal SSI savings | B32: =$B$22 -> 2.22139 | C32: =$B$22 -> 2.22139 | D32: =$B$22 -> 2.22139 | F32: Held constant in real terms
A33: Total government-wide improvement | B33: =B30+B31+B32 -> 72.629354 | C33: =C30+C31+C32 -> 76.524745 | D33: =D30+D31+D32 -> 82.196011 | F33: Calculated
A34: SS gap before healthcare waterfall | B34: =MAX(0,SS_Year_0_4_10!B22-SS_Year_0_4_10!B21-B30-B31) -> 217.67979 | C34: =MAX(0,SS_Year_0_4_10!C22-SS_Year_0_4_10!C21-C30-C31) -> 229.89468 | D34: =MAX(0,SS_Year_0_4_10!D22-SS_Year_0_4_10!D21-D30-D31) -> 193.22434 | F34: Calculated
A35: Healthcare transfer to Social Security | B35: =MIN(B34,SS_Year_0_4_10!B26) -> 217.67979 | C35: =MIN(C34,SS_Year_0_4_10!C26) -> 229.89468 | D35: =MIN(D34,SS_Year_0_4_10!D26) -> 193.22434 | F35: Calculated
A36: Residual Treasury support | B36: =MAX(0,B34-B35) -> 0 | C36: =MAX(0,C34-C35) -> 0 | D36: =MAX(0,D34-D35) -> 0 | F36: Calculated
A37: Residual healthcare profit after SS | B37: =MAX(0,SS_Year_0_4_10!B26-B35) -> 26.829705 | C37: =MAX(0,SS_Year_0_4_10!C26-C35) -> 14.614811 | D37: =MAX(0,SS_Year_0_4_10!D26-D35) -> 51.285156 | F37: Calculated
A38: NIRF allocation | B38: =B37/2 -> 13.414853 | C38: =C37/2 -> 7.3074054 | D38: =D37/2 -> 25.642578 | F38: Calculated
A39: Citizen Wealth Fund allocation | B39: =B37/2 -> 13.414853 | C39: =C37/2 -> 7.3074054 | D39: =D37/2 -> 25.642578 | F39: Calculated
A40: Consolidated federal balance | B40: =SS_Year_0_4_10!$B$11+SS_Year_0_4_10!$B$12+B32-B34 -> 183.98577 | C40: =SS_Year_0_4_10!$B$11+SS_Year_0_4_10!$B$12+C32-C34 -> 171.77087 | D40: =SS_Year_0_4_10!$B$11+SS_Year_0_4_10!$B$12+D32-D34 -> 208.44122 | F40: Calculated
A42: IMPLEMENTATION REQUIREMENT
A43: Because the policy bars SSNs for noncitizens while still collecting employment contributions, the government must issue a separate Federal Work and Tax Number linked to immigration status, payroll reporting, withholding, and employer matching. Without that identifier, the revenue mechanism cannot operate.

Sheet National_Continuity
A1: NATIONAL CONTINUITY CONTRIBUTION | ENTERPRISE-VALUATION LEVY
A2: Annual 0.73% levy on the assessed enterprise value of every public or private company valued above $1 million. Social Security receives the amount needed for annual balance; remaining proceeds capitalize the NIRF.
A4: A. CENTRAL REVENUE MODEL
A5: Input | B5: Central value | C5: Unit | D5: Formula / treatment | E5: Validation posture | F5: Source | G5: Status
A6: Covered assessed enterprise value | B6: 68000 | C6: $B | D6: Central bookable base for companies above $1M | E6: Studied central estimate from Federal Reserve business/equity balance sheets, adjusted for threshold and overlap | F6: https://www.federalreserve.gov/releases/z1/preview/html/b103.htm ; https://www.federalreserve.gov/releases/z1/preview/html/l224.htm | G6: Studied estimate
A7: Annual contribution rate | B7: 0.0073 | C7: Flat rate | D7: Paid at annual federal business registration | E7: Policy Book / adopted parameter | G7: Adopted
A8: Gross annual NCC revenue | B8: =B6*B7 -> 496.4 | C8: $B | D8: Covered valuation × 0.73% | E8: $7.3B per $1T of covered value | G8: Calculated
A9: Registration threshold | B9: 1 | C9: $M enterprise value | D9: Companies at or below threshold excluded | E9: Common-control aggregation prevents fragmentation | G9: Adopted
A10: Annual real valuation growth | B10: 0.012 | C10: Rate | D10: Held equal to existing real contribution-base growth | E10: Central projection assumption | G10: Modeled
A12: B. VALUATION-BASE SENSITIVITY
A13: Covered enterprise value ($T) | B13: Revenue at 0.73% ($B) | C13: Year 0 SS use ($B) | D13: Year 0 NIRF residual ($B) | E13: Interpretation | F13: Source | G13: Status
A14: 50 | B14: =A14*1000*$B$7 -> 365 | C14: =MIN(B14,SS_Year_0_4_10!B23) -> 205.67979 | D14: =MAX(0,B14-C14) -> 159.32021 | E14: Lower assessable-base case | G14: Sensitivity
A15: 60 | B15: =A15*1000*$B$7 -> 438 | C15: =MIN(B15,SS_Year_0_4_10!B23) -> 205.67979 | D15: =MAX(0,B15-C15) -> 232.32021 | E15: Moderate assessable-base case | G15: Sensitivity
A16: 68 | B16: =A16*1000*$B$7 -> 496.4 | C16: =MIN(B16,SS_Year_0_4_10!B23) -> 205.67979 | D16: =MAX(0,B16-C16) -> 290.72021 | E16: Central bookable case | G16: Central
A17: 75 | B17: =A17*1000*$B$7 -> 547.5 | C17: =MIN(B17,SS_Year_0_4_10!B23) -> 205.67979 | D17: =MAX(0,B17-C17) -> 341.82021 | E17: Broad coverage case | G17: Sensitivity
A18: 85 | B18: =A18*1000*$B$7 -> 620.5 | C18: =MIN(B18,SS_Year_0_4_10!B23) -> 205.67979 | D18: =MAX(0,B18-C18) -> 414.82021 | E18: High valuation case | G18: Sensitivity
A20: C. YEAR 0 / YEAR 4 / YEAR 10 WATERFALL
A21: Measure | B21: Year 0 | C21: Year 4 | D21: Year 10 | E21: Treatment | F21: Formula basis | G21: Status
A22: Gross NCC revenue | B22: =$B$8*(1+$B$10)^0 -> 496.4 | C22: =$B$8*(1+$B$10)^4 -> 520.65953 | D22: =$B$8*(1+$B$10)^10 -> 559.2898 | F22: Central base grows 1.2% real annually | G22: Calculated
A23: SS gap before NCC | B23: =SS_Year_0_4_10!B23 -> 205.67979 | C23: =SS_Year_0_4_10!C23 -> 217.89468 | D23: =SS_Year_0_4_10!D23 -> 181.22434 | F23: Citizen-only SS result before healthcare transfer | G23: Calculated
A24: NCC transfer to Social Security | B24: =MIN(B22,B23) -> 205.67979 | C24: =MIN(C22,C23) -> 217.89468 | D24: =MIN(D22,D23) -> 181.22434 | F24: Lesser of NCC revenue and SS gap | G24: Calculated
A25: Social Security ending balance | B25: =B24-B23 -> 0 | C25: =C24-C23 -> 0 | D25: =D24-D23 -> 0 | F25: Dedicated balance after NCC | G25: Calculated
A26: NIRF residual from NCC | B26: =MAX(0,B22-B24) -> 290.72021 | C26: =MAX(0,C22-C24) -> 302.76485 | D26: =MAX(0,D22-D24) -> 378.06546 | F26: NCC revenue remaining after SS breakeven | G26: Calculated
A27: Residual Treasury support | B27: =MAX(0,B23-B24) -> 0 | C27: =MAX(0,C23-C24) -> 0 | D27: =MAX(0,D23-D24) -> 0 | F27: Only if NCC revenue is insufficient | G27: Calculated
A28: NHDC / healthcare transfer to SS | B28: 0 | C28: 0 | D28: 0 | F28: NHDC fully untied from Social Security | G28: Adopted
A29: Healthcare reserve retained | B29: 120 | C29: 120 | D29: 120 | F29: Protected reserve | G29: Adopted
A30: Healthcare surplus after reserve | B30: 244.50949 | C30: 244.50949 | D30: 244.50949 | F30: Independent healthcare waterfall | G30: Calculated
A31: Healthcare R&D / capacity allocation | B31: 0 | C31: 0 | D31: 0 | F31: Placeholder until explicit annual appropriation is costed | G31: Unbooked
A32: Healthcare residual to NIRF | B32: =(B30-B31)/2 -> 122.25475 | C32: =(C30-C31)/2 -> 122.25475 | D32: =(D30-D31)/2 -> 122.25475 | F32: 50% after reserve and approved healthcare needs | G32: Calculated
A33: Healthcare residual to CWF | B33: =(B30-B31)/2 -> 122.25475 | C33: =(C30-C31)/2 -> 122.25475 | D33: =(D30-D31)/2 -> 122.25475 | F33: 50% after reserve and approved healthcare needs | G33: Calculated
A34: Strict Treasury balance | B34: =SS_Year_0_4_10!$B$11+Noncitizen_SS_Model!B32-B27 -> 37.156061 | C34: =SS_Year_0_4_10!$B$11+Noncitizen_SS_Model!C32-C27 -> 37.156061 | D34: =SS_Year_0_4_10!$B$11+Noncitizen_SS_Model!D32-D27 -> 37.156061 | F34: General balance + SSI saving − residual Treasury backstop | G34: Calculated
A35: Consolidated federal balance | B35: =Budget_0_4_10!B23 -> 992.18577 | C35: =Budget_0_4_10!C23 -> 1004.2304 | D35: =Budget_0_4_10!D23 -> 1079.531 | F35: Fully inclusive budget path with the NLA ramp | G35: Calculated
A37: D. POLICY CONTROLS
A38: Control | B38: Rule | C38: Purpose | D38: Status
A39: Public-company valuation | B39: Annual average market capitalization plus debt less unrestricted cash | C39: Reduces registration-date manipulation | D39: Required
A40: Private-company valuation | B40: Recent arm's-length valuation, audited financing value, sector multiple, adjusted net assets, then federal appraisal | C40: Creates a repeatable hierarchy | D40: Required
A41: Common-control aggregation | B41: Affiliated entities valued as one economic enterprise | C41: Prevents artificial division below $1M | D41: Required
A42: Liquidity protection | B42: Quarterly installments or secured deferral for qualified private firms | C42: Prevents forced liquidation without erasing liability | D42: Required
A43: Revenue routing | B43: Social Security to annual breakeven, then NIRF | C43: Unties NHDC from Social Security | D43: Required

Sheet Revenue_Validation
A1: REVENUE RESEARCH INITIATIVE | VALIDATION REGISTER
A2: All revenue mechanisms were reviewed against Policy Book v89. LVT is intentionally carried forward unchanged and excluded from this validation initiative.
A4: Method / input | B4: Prior posture | C4: Research basis | D4: Studied central estimate ($B) | E4: Low ($B) | F4: High ($B) | G4: Budget treatment | H4: Confidence | I4: Primary references
A5: National Continuity covered enterprise value | B5: Modeled $23T | C5: Federal Reserve Financial Accounts corporate equity, business debt, cash, and noncorporate business equity; adjusted for >$1M threshold and double counting | D5: 68000 | E5: 60000 | F5: 78000 | G5: 0.73% gross dedicated receipt; SS first, NIRF residual | H5: Medium | I5: https://www.federalreserve.gov/releases/z1/preview/html/b103.htm ; https://www.federalreserve.gov/releases/z1/preview/html/l224.htm
A6: Resident Contributor employment and earnings base | B6: Modeled from ACS/MPI and BLS | C6: ACS citizenship/workforce framework plus BLS foreign-born earnings; central remains 14.866M workers and $46,000 average liquid earnings | D6: 683.82 | E6: 610 | F6: 760 | G6: 7% employee; employer 7% on employer-covered compensation | H6: Medium | I6: https://www.census.gov/topics/population/foreign-born/data/tables/acs-tables.html ; https://www.bls.gov/news.release/forbrn.t05.htm
A7: Noncitizen OASDI benefit exclusion | B7: Modeled $18B | C7: SSA publishes OASDI totals and totalization data but no complete current citizenship cross-tab; bracketed using 0.9M-1.5M recipients and $1,100-$1,350 monthly benefit | D7: 18 | E7: 11.88 | F7: 24.3 | G7: Dedicated Social Security saving | H7: Medium-low | I7: https://www.ssa.gov/policy/docs/statcomps/supplement/2024/ ; https://www.ssa.gov/policy/about/oasdi-reference.html
A8: Federal SSI noncitizen exclusion | B8: Verified annualized flow | C8: SSA SSI Annual Statistical Report noncitizen recipient and payment tables | D8: 2.221 | E8: 2 | F8: 2.5 | G8: General Government saving | H8: High | I8: https://www.ssa.gov/policy/docs/statcomps/ssi_asr/2024/
A9: Carbon Tax | B9: Unbooked; rate unspecified | C9: 2024 U.S. energy-related CO2 emissions; studied central rate $25/metric ton with 10% mature behavioral erosion | D9: 107.4 | E9: 78.7 | F9: 143.2 | G9: General Treasury | H9: Medium | I9: https://www.eia.gov/environment/emissions/carbon/
A10: Sin sales surtax | B10: Booked $26.5B | C10: 5% statutory rate applied to alcohol, tobacco, gambling, and marijuana consumer-sales study; refreshed central base $530B | D10: 26.5 | E10: 23 | F10: 30 | G10: Dedicated catastrophic-care revenue | H10: Medium | I10: https://apps.bea.gov/iTable/?reqid=19&step=2 ; https://www.census.gov/programs-surveys/economic-census.html
A11: Spectrum stewardship auctions and rent | B11: Unbooked | C11: FCC/NTIA historical auction proceeds, plus prospective annual rent, transfer, and vacancy fees; annualized across auction cycles | D11: 12 | E11: 7 | F11: 18 | G11: $6B NIRF capital, $5B Treasury, $1B administration | H11: Medium | I11: https://www.fcc.gov/auctions-summary ; https://www.ntia.gov/report/2024/2023-commercial-spectrum-enhancement-act-csea-report/part-i-1710-1755-mhz-band-aws-1
A12: National laboratory patent marketplace | B12: Unbooked | C12: Existing federal lab licensing and royalty income scaled through unified marketplace and commercialization auctions | D12: 0.5 | E12: 0.25 | F12: 1 | G12: $0.4B net General Treasury after $0.1B administration | H12: Medium-low | I12: https://www.energy.gov/sites/prod/files/2016/06/f33/Technology%20Transfer%20Report%20to%20Congress%20FY14.pdf ; https://www.energy.gov/sites/default/files/2024-05/TTWG%20Licensing%20Guide%20and%20Sample%20License%202024.pdf
A13: Federal Enterprise Data Services | B13: Unbooked | C13: Paid reliability, API, processing, redistribution, and international institutional tiers layered over free public data | D13: 3 | E13: 1.5 | F13: 5 | G13: $2B net General Treasury after $1B service cost | H13: Medium-low | I13: https://www.bea.gov/data ; https://www.census.gov/data.html ; https://www.noaa.gov/information-technology/open-data-dissemination
A14: Strategic industrial campus leases and services | B14: Unbooked | C14: Ground leases, utilities, testing subscriptions, security, certification, and profit royalties at mature federally prepared campuses | D14: 15 | E14: 8 | F14: 25 | G14: $10B net General Treasury after $5B campus operations | H14: Medium-low | I14: https://www.gao.gov/products/gao-24-106084 ; https://www.eda.gov/funding/programs/tech-hubs
A15: National Pipeline Corridor capacity auctions | B15: Unbooked | C15: BLM right-of-way rents and competitive capacity allocation expanded to a national corridor system | D15: 4 | E15: 2 | F15: 7 | G15: $3.5B net General Treasury after $0.5B administration | H15: Medium-low | I15: https://www.blm.gov/sites/blm.gov/files/ObtainingaROWPamphlet.pdf
A16: NHDC international product and manufacturing licenses | B16: Partly proxied by exports | C16: Royalty and contract-manufacturing licenses separated from physical export margin | D16: 12 | E16: 6 | F16: 20 | G16: Dedicated healthcare commercial earnings | H16: Medium-low | I16: https://www.cms.gov/data-research/statistics-trends-and-reports/national-health-expenditure-data ; https://www.fda.gov/drugs/generic-drugs/office-generic-drugs-2024-annual-report
... A29: LVT | B29: Excluded by instruction | C29: No change made to base, rate, validation sheet, or booked revenue | D29: 2232.929 | E29: 2232.929 | F29: 2232.929 | G29: General Treasury | H29: Carried unchanged | I29: Existing workbook

Sheet Additional_Revenue
A1: ADDITIONAL POLICY-BOOK REVENUE | STUDIED CENTRAL ESTIMATES
A2: These lines were absent from the prior budget headline. Gross external receipts, operating costs, dedicated routing, and overlap controls are shown separately.
A4: Revenue method | B4: Gross receipt ($B) | C4: Direct operating cost ($B) | D4: Net fiscal contribution ($B) | E4: General Treasury ($B) | F4: Dedicated funds ($B) | G4: Treatment | H4: Source / basis
A5: Carbon Tax | B5: 107.4 | C5: 4 | D5: =B5-C5 -> 103.4 | E5: =D5 -> 103.4 | F5: 0 | G5: $25/t on 2024 energy CO2 with 10% mature erosion | H5: https://www.eia.gov/environment/emissions/carbon/
A6: Spectrum stewardship | B6: 12 | C6: 1 | D6: =B6-C6 -> 11 | E6: 5 | F6: 6 | G6: Auction/rent cycle annualization; $6B NIRF capital | H6: https://www.fcc.gov/auctions-summary
A7: National lab patent marketplace | B7: 0.5 | C7: 0.1 | D7: =B7-C7 -> 0.4 | E7: =D7 -> 0.4 | F7: 0 | G7: Unified licenses, royalties, exclusivity auctions | H7: https://www.energy.gov/sites/prod/files/2016/06/f33/Technology%20Transfer%20Report%20to%20Congress%20FY14.pdf
A8: Federal Enterprise Data Services | B8: 3 | C8: 1 | D8: =B8-C8 -> 2 | E8: =D8 -> 2 | F8: 0 | G8: Premium reliability and enterprise service tiers | H8: https://www.census.gov/data.html
A9: Industrial campus leases/services | B9: 15 | C9: 5 | D9: =B9-C9 -> 10 | E9: =D9 -> 10 | F9: 0 | G9: Ground leases, utilities, testing, security, royalties | H9: https://www.eda.gov/funding/programs/tech-hubs
A10: Pipeline corridor capacity auctions | B10: 4 | C10: 0.5 | D10: =B10-C10 -> 3.5 | E10: =D10 -> 3.5 | F10: 0 | G10: Capacity auctions and ROW rents | H10: https://www.blm.gov/sites/blm.gov/files/ObtainingaROWPamphlet.pdf
A11: NHDC international licenses | B11: 12 | C11: 0 | D11: =B11-C11 -> 12 | E11: 0 | F11: 12 | G11: Separate from physical export margin | H11: https://www.fda.gov/drugs/generic-drugs
A12: NLA institutional/international | B12: 12 | C12: 0 | D12: =B12-C12 -> 12 | E12: 0 | F12: 12 | G12: Net distributable public lending/servicing earnings | H12: https://www.federalreserve.gov/releases/g19/current/
A13: Commercial space infrastructure | B13: 5 | C13: 2 | D13: =B13-C13 -> 3 | E13: =D13 -> 3 | F13: 0 | G13: Orbital and launch infrastructure services | H13: https://www.faa.gov/space
A14: Patent troll penalties | B14: 0.5 | C14: 0 | D14: =B14-C14 -> 0.5 | E14: =D14 -> 0.5 | F14: 0 | G14: Deterrence revenue; not a major fiscal pillar | H14: https://www.uspto.gov/ip-policy/patent-policy
A15: NIRF distributable return | B15: 150 | C15: 0 | D15: =B15-C15 -> 150 | E15: =D15 -> 150 | F15: 0 | G15: 50% of studied mature 4% real return on $7.5T corpus | H15: https://www.federalreserve.gov/releases/z1/
A16: TOTAL NEWLY BOOKED | B16: =SUM(B5:B15) -> 321.4 | C16: =SUM(C5:C15) -> 13.6 | D16: =SUM(D5:D15) -> 307.8 | E16: =SUM(E5:E15) -> 277.8 | F16: =SUM(F5:F15) -> 30 | G16: Excludes Social Security payment-accuracy saving

Sheet Budget_0_4_10
A1: BUDGET SUMMARY | NLA STARTUP, FULL-TERM GROWTH, AND MATURITY
A2: Year 0 uses the startup NLA portfolio, Year 4 uses the full-term growth portfolio, and Year 10 uses the mature NLA portfolio. NCC uses the validated $68T Year 0 base and 1.2% annual real valuation growth.
A4: Fiscal line | B4: Year 0 | C4: Year 4 | D4: Year 10
A5: NLA domestic distributable profit | B5: =NLA_Model!E21 -> 21.471784 | C5: =NLA_Model!E22 -> 67.71298 | D5: =NLA_Model!E23 -> 154.13732
A6: Citizen + employer contributions | B6: =SS_Hybrid_2024!D9 -> 976.39047 | C6: =SS_Hybrid_2024!D9*(1+SS_Year_0_4_10!$B$8)^4 -> 1024.1076 | D6: =SS_Hybrid_2024!D9*(1+SS_Year_0_4_10!$B$8)^10 -> 1100.0911
A7: Trust investment income | B7: =SS_Year_0_4_10!B20 -> 193.05 | C7: =SS_Year_0_4_10!C20 -> 193.05 | D7: =SS_Year_0_4_10!D20 -> 193.05
A8: Resident Contributor incremental contributions | B8: =Noncitizen_SS_Model!B30 -> 52.407964 | C8: =Noncitizen_SS_Model!C30 -> 54.96919 | D8: =Noncitizen_SS_Model!D30 -> 59.047622
A9: Noncitizen OASDI benefit savings | B9: =Noncitizen_SS_Model!B31 -> 18 | C9: =Noncitizen_SS_Model!C31 -> 19.334165 | D9: =Noncitizen_SS_Model!D31 -> 20.926999
A10: NLA institutional / international earnings | B10: =12 -> 12 | C10: =12 -> 12 | D10: =12 -> 12
A11: Social Security funding before NCC | B11: =SUM(B5:B10) -> 1273.3202 | C11: =SUM(C5:C10) -> 1371.1739 | D11: =SUM(D5:D10) -> 1539.2531
A12: Net OASDI obligation after $6B payment-accuracy saving | B12: =SS_Year_0_4_10!B22 -> 1479 | C12: =SS_Year_0_4_10!C22 -> 1589.0686 | D12: =SS_Year_0_4_10!D22 -> 1720.4774
A13: Social Security gap before NCC | B13: =MAX(0,B12-B11) -> 205.67979 | C13: =MAX(0,C12-C11) -> 217.89468 | D13: =MAX(0,D12-D11) -> 181.22434
A14: Gross National Continuity Contribution | B14: =National_Continuity!B22 -> 496.4 | C14: =National_Continuity!C22 -> 520.65953 | D14: =National_Continuity!D22 -> 559.2898
A15: NCC transfer to Social Security | B15: =MIN(B13,B14) -> 205.67979 | C15: =MIN(C13,C14) -> 217.89468 | D15: =MIN(D13,D14) -> 181.22434
A16: Social Security ending balance | B16: =B11+B15-B12 -> 0 | C16: =C11+C15-C12 -> 0 | D16: =D11+D15-D12 -> 0
A17: NCC residual to NIRF | B17: =MAX(0,B14-B15) -> 290.72021 | C17: =MAX(0,C14-C15) -> 302.76485 | D17: =MAX(0,D14-D15) -> 378.06546
A18: Operating General Treasury Revenue | B18: =Tax_Revenue_2024!D33 -> 5710.9312 | C18: =Tax_Revenue_2024!D33 -> 5710.9312 | D18: =Tax_Revenue_2024!D33 -> 5710.9312
A19: Total Government Revenue | B19: =Total_Government_Revenue!B24-NLA_Model!E23+NLA_Model!E21-National_Continuity!D22+National_Continuity!B22 -> 8907.1381 | C19: =Total_Government_Revenue!B24-NLA_Model!E23+NLA_Model!E22-National_Continuity!D22+National_Continuity!C22 -> 8977.6388 | D19: =Total_Government_Revenue!B24 -> 9102.6934
A20: General Government balance | B20: =Deficit_Views!B43 -> 318.95606 | C20: =Deficit_Views!B43 -> 318.95606 | D20: =Deficit_Views!B43 -> 318.95606
A21: Healthcare balance | B21: =Deficit_Views!B44 -> 376.50949 | C21: =Deficit_Views!B44 -> 376.50949 | D21: =Deficit_Views!B44 -> 376.50949
A22: Strict Treasury balance | B22: =B20-National_Continuity!B27 -> 318.95606 | C22: =C20-National_Continuity!C27 -> 318.95606 | D22: =D20-National_Continuity!D27 -> 318.95606
A23: Consolidated replacement surplus | B23: =B20+B21+B17+6 -> 992.18577 | C23: =C20+C21+C17+6 -> 1004.2304 | D23: =D20+D21+D17+6 -> 1079.531

Sheet Household_Incidence
A1: ILLUSTRATIVE HOUSEHOLD INCIDENCE | CURRENT 2024 FEDERAL CODE VS PROPOSED 10% + 3% + HSA TIER
A2: Single-filer illustrations in 2024 dollars. Current burden includes federal individual income tax and employee payroll tax. Proposed burden includes the 10% liquid-income tax, 3% citizen Social Security contribution, and the assigned citizen HSA tier. Employer-side contributions, state taxes, credits, itemized deductions, and current insurance premiums are excluded.
A4: Profile | B4: Wages / taxable pension ($) | C4: SS benefits ($) | D4: HSA tier | E4: Current taxable income ($) | F4: Current federal income tax ($) | G4: Current employee payroll tax ($) | H4: Current total burden ($) | I4: Proposed 10% tax ($) | J4: Proposed 3% SS ($) | K4: Proposed HSA ($) | L4: Proposed total burden ($) | M4: Change ($) | N4: Change (% of liquid income)
A5: Nurse | B5: 80000 | C5: 0 | D5: 0.03 | E5: =MAX(0,B5-14600) -> 65400 | F5: =MIN(E5,11600)*10%+MAX(0,MIN(E5,47150)-11600)*12%+MAX(0,MIN(E5,100525)-47150)*22%+MAX(0,MIN(E5,191950)-100525)*24%+MAX(0,MIN(E5,243725)-191950)*32%+MAX(0,MIN(E5,609350)-243725)*35%+MAX(0,E5-609350)*37% -> 9441 | G5: =MIN(B5,168600)*6.2%+B5*1.45%+MAX(0,B5-200000)*0.9% -> 6120 | H5: =F5+G5 -> 15561 | I5: =B5*10% -> 8000 | J5: =B5*3% -> 2400 | K5: =B5*D5 -> 2400 | L5: =SUM(I5:K5) -> 12800 | M5: =L5-H5 -> -2761 | N5: =M5/B5 -> -0.0345125
A6: Machinist | B6: 70000 | C6: 0 | D6: 0.03 | E6: =MAX(0,B6-14600) -> 55400 | F6: =MIN(E6,11600)*10%+MAX(0,MIN(E6,47150)-11600)*12%+MAX(0,MIN(E6,100525)-47150)*22%+MAX(0,MIN(E6,191950)-100525)*24%+MAX(0,MIN(E6,243725)-191950)*32%+MAX(0,MIN(E6,609350)-243725)*35%+MAX(0,E6-609350)*37% -> 7241 | G6: =MIN(B6,168600)*6.2%+B6*1.45%+MAX(0,B6-200000)*0.9% -> 5355 | H6: =F6+G6 -> 12596 | I6: =B6*10% -> 7000 | J6: =B6*3% -> 2100 | K6: =B6*D6 -> 2100 | L6: =SUM(I6:K6) -> 11200 | M6: =L6-H6 -> -1396 | N6: =M6/B6 -> -0.019942857
A7: Retiree | B7: 60000 | C7: 30000 | D7: 0.02 | E7: =MAX(0,B7+MIN(85%*C7,85%*MAX(0,B7+50%*C7-34000)+MIN(4500,50%*C7))-16550) -> 68950 | F7: =MIN(E7,11600)*10%+MAX(0,MIN(E7,47150)-11600)*12%+MAX(0,MIN(E7,100525)-47150)*22%+MAX(0,MIN(E7,191950)-100525)*24%+MAX(0,MIN(E7,243725)-191950)*32%+MAX(0,MIN(E7,609350)-243725)*35%+MAX(0,E7-609350)*37% -> 10222 | G7: =0 -> 0 | H7: =F7+G7 -> 10222 | I7: =B7*10% -> 6000 | J7: =B7*3% -> 1800 | K7: =B7*D7 -> 1200 | L7: =SUM(I7:K7) -> 9000 | M7: =L7-H7 -> -1222 | N7: =M7/B7 -> -0.020366667
A8: Surgeon | B8: 400000 | C8: 0 | D8: 0.05 | E8: =MAX(0,B8-14600) -> 385400 | F8: =MIN(E8,11600)*10%+MAX(0,MIN(E8,47150)-11600)*12%+MAX(0,MIN(E8,100525)-47150)*22%+MAX(0,MIN(E8,191950)-100525)*24%+MAX(0,MIN(E8,243725)-191950)*32%+MAX(0,MIN(E8,609350)-243725)*35%+MAX(0,E8-609350)*37% -> 105264.75 | G8: =MIN(B8,168600)*6.2%+B8*1.45%+MAX(0,B8-200000)*0.9% -> 18053.2 | H8: =F8+G8 -> 123317.95 | I8: =B8*10% -> 40000 | J8: =B8*3% -> 12000 | K8: =B8*D8 -> 20000 | L8: =SUM(I8:K8) -> 72000 | M8: =L8-H8 -> -51317.95 | N8: =M8/B8 -> -0.12829488
A10: Interpretation: these are transparent examples, not a distributional microsimulation. The retiree receives $30,000 of Social Security benefits. Current law taxes the applicable portion of those benefits, while the proposed liquid-income base excludes Social Security benefits entirely.
A12: Source / assumption | B12: Value | C12: URL | D12: Note
A13: 2024 single standard deduction | B13: 14600 | C13: https://www.irs.gov/pub/irs-drop/rp-23-34.pdf | D13: IRS Revenue Procedure 2023-34
A14: 2024 additional aged single deduction | B14: 1950 | C14: https://www.irs.gov/pub/irs-drop/rp-23-34.pdf | D14: Used for retiree illustration
A15: 2024 OASDI wage cap | B15: 168600 | C15: https://www.ssa.gov/benefits/retirement/planner/maxtax.html | D15: Employee rate 6.2%
A16: Employee Medicare rate | B16: 0.0145 | C16: https://www.ssa.gov/oact/progdata/taxRates.html | D16: No wage cap
A17: Additional Medicare threshold, single | B17: 200000 | C17: https://www.irs.gov/taxtopics/tc560 | D17: 0.9% above threshold
A18: Proposed HSA tiers | B18: 0.02 | C18: Internal policy model | D18: Illustrations assign retiree 2%, workers 3%, surgeon 5%

Sheet NCC_Carveout
A1: NATIONAL CONTINUITY CONTRIBUTION | FAMILY FARM AND OPERATING SMALL-BUSINESS CARVE-OUT
A2: The current $1 million threshold reaches many asset-rich but cash-constrained farms and machine shops. This sheet publishes the revenue cost of removing portions of the $68 trillion central base and tests a qualified operating-enterprise allowance.
A4: Input | B4: Central value | C4: Unit | D4: Source / basis | E4: Policy treatment | F4: Status | G4: Low case | H4: High case
A5: Central covered enterprise-value base | B5: 68000 | C5: $B | D5: National_Continuity | E5: Before carve-out | F5: Studied | G5: 68000 | H5: 68000
A6: NCC rate | B6: 0.0073 | C6: Annual rate | D6: Adopted policy | E6: Flat rate | F6: Adopted | G6: 0.0073 | H6: 0.0073
A7: Median family-farm household wealth | B7: 1.44 | C7: $M | D7: USDA ERS, 2023 | E7: Shows $1M threshold reaches ordinary family farms | F7: External | G7: 1.44 | H7: 1.6
A8: Small family farms share | B8: 0.86 | C8: Share of farms | D8: USDA ERS, 2024 | E8: Political exposure indicator | F8: External | G8: 0.86 | H8: 0.88
A9: Recommended qualified operating-enterprise allowance | B9: 5 | C9: $M | D9: Model design | E9: First $5M exempt for qualifying family farms and closely held operating manufacturers | F9: Proposal | G9: 3 | H9: 10
A10: Full-rate threshold after phase-in | B10: 10 | C10: $M | D10: Model design | E10: 0.25% between allowance and full-rate threshold; 0.73% above threshold | F10: Proposal | G10: 7.5 | H10: 15
A12: Excluded valuation from central base ($T) | B12: Annual revenue loss ($B) | C12: Year 10 surplus after carve-out ($B) | D12: Share of $68T base removed | E12: Interpretation | F12: Status
A13: 0.5 | B13: =A13*1000*$B$6 -> 3.65 | C13: =Budget_0_4_10!D23-B13*(1+National_Continuity!$B$10)^10 -> 1075.4186 | D13: =A13/68 -> 0.0073529412 | E13: Sensitivity; registry data required | F13: Modeled
A14: 1 | B14: =A14*1000*$B$6 -> 7.3 | C14: =Budget_0_4_10!D23-B14*(1+National_Continuity!$B$10)^10 -> 1071.3062 | D14: =A14/68 -> 0.014705882 | E14: Sensitivity; registry data required | F14: Modeled
A15: 2 | B15: =A15*1000*$B$6 -> 14.6 | C15: =Budget_0_4_10!D23-B15*(1+National_Continuity!$B$10)^10 -> 1063.0813 | D15: =A15/68 -> 0.029411765 | E15: Sensitivity; registry data required | F15: Modeled
A16: 3 | B16: =A16*1000*$B$6 -> 21.9 | C16: =Budget_0_4_10!D23-B16*(1+National_Continuity!$B$10)^10 -> 1054.8565 | D16: =A16/68 -> 0.044117647 | E16: Sensitivity; registry data required | F16: Modeled
A17: 5 | B17: =A17*1000*$B$6 -> 36.5 | C17: =Budget_0_4_10!D23-B17*(1+National_Continuity!$B$10)^10 -> 1038.4068 | D17: =A17/68 -> 0.073529412 | E17: Sensitivity; registry data required | F17: Modeled
A18: 8 | B18: =A18*1000*$B$6 -> 58.4 | C18: =Budget_0_4_10!D23-B18*(1+National_Continuity!$B$10)^10 -> 1013.7322 | D18: =A18/68 -> 0.11764706 | E18: Sensitivity; registry data required | F18: Modeled
A21: Recommended statutory design: exclude the first $5 million of qualified operating enterprise value for family farms and closely held manufacturers; apply 0.25% from $5 million to $10 million; apply 0.73% above $10 million. Qualification requires active domestic operations, majority family or employee ownership, a five-year holding test, common-control aggregation, and recapture when assets are sold or converted to passive holdings. The fiscal headline remains unchanged until registry data validates the excluded base.
A23: Source | B23: URL | C23: Evidence used | D23: Caution
A24: USDA ERS, Farm Household Wealth | B24: https://www.ers.usda.gov/topics/farm-economy/farm-household-well-being/income-and-wealth-in-context | C24: Median farm-household wealth near or above $1M | D24: Household wealth is not enterprise value
A25: USDA ERS, Farms and Ranches at a Glance 2024 | B25: https://ers.usda.gov/sites/default/files/_laserfiche/publications/110560/EIB-283.pdf | C25: Small family farms dominate farm count | D25: Sales class differs from valuation
A26: USDA NASS, 2024 Land Values | B26: https://www.nass.usda.gov/Publications/Highlights/2024/2024LandValuesCashRents.pdf | C26: Farm real estate averaged $4,170 per acre | D26: Includes buildings
A27: Census Annual Business Survey | B27: https://www.census.gov/programs-surveys/abs.html | C27: Registry validation source for operating firms | D27: No current national enterprise-value distribution
